Workbook

Sheet Cover
B2: Lumina Renewables S.p.A.: Monte Carlo DCF Valuation
B3: Alessandro Radice · fictional mid-market Italian solar and wind operator · educational project, not investment advice
B5: Sheet | E5: What it holds
B6: Assumptions | E6: Distributions of the six drivers, fixed parameters and the windfall-tax event (blue cells)
B7: DCF Base Case | E7: Five-year unlevered DCF at the most-likely value of every driver
B8: Simulation | E8: 2,000 live iterations: each row turns one set of random numbers into drivers and a value per share
B9: Random Draws | E9: The random numbers behind each row: the first 2,000 of the 50,000 in the Python run (seed 113)
B10: Results | E10: Mean, median, percentiles, probabilities and the histogram of the live iterations
B11: Sensitivity | E11: Which driver moves value most: live correlations and the 50,000-run rank correlations
B12: Windfall | E12: The tax risk modelled as an event that happens or not, on the same random numbers
B13: Convergence | E13: How much the median and the tails move between runs, from 250 to 50,000 iterations
B14: Price Paths | E14: Geometric Brownian Motion paths of the share price over five years
B15: Checks | E15: Every live iteration recomputed in Python and compared with Excel
B17: Colour code: blue = input, black = formula, green = link to another sheet.
B19: Headline results
B20: Value per share | C20: Live (2,000) | D20: Python (50,000) | E20: Note
B21: Base case (most-likely inputs) | C21: ='DCF Base Case'!C36 -> 14.916493 | D21: 14.916493 | E21: Single-point DCF
B22: Mean | C22: =Results!C6 -> 13.40285 | D22: 13.225795
B23: Median (P50) | C23: =Results!C7 -> 12.553903 | D23: 12.487061 | E23: The typical outcome
B24: Downside (P5) | C24: =Results!C9 -> 5.4605247 | D24: 5.3544624 | E24: One run in twenty is worse
B25: Upside (P95) | C25: =Results!C13 -> 24.176302 | D25: 23.61234 | E25: One run in twenty is better
B26: P(value > market price) | C26: =Results!C15 -> 0.58 | D26: 0.57478 | E26: Market price on the Assumptions sheet
B27: Base case above median | C27: =C21/C23-1 -> 0.18819564 | D27: 0.19455594 | E27: Why the point estimate flatters
B29: The live column moves with the blue inputs. The Python column is the 50,000-iteration headline and stays fixed; the two differ because 2,000 draws carry sampling noise (see Convergence).

Sheet Assumptions
B2: Assumptions
B3: Change any blue cell: the base case and all live iterations recalculate
B5: Driver | C5: Distribution | D5: Min / mean | E5: Mode / st. dev. | F5: Max | G5: Why
B6: Revenue growth (p.a.) | C6: Triangular | D6: 0.04 | E6: 0.09 | F6: 0.14 | G6: Contracted capacity plus new projects; skewed neither way
B7: EBITDA margin | C7: Triangular | D7: 0.36 | E7: 0.42 | F7: 0.46 | G7: Long tail down: curtailment, lower captured prices
B8: WACC | C8: Normal | D8: 0.085 | E8: 0.011 | G8: Capital-intensive and rate-sensitive; clipped to the floor and cap below
B9: Tax rate | C9: Triangular | D9: 0.24 | E9: 0.26 | F9: 0.35 | G9: IRES plus IRAP near 26%; tail to 35% for windfall-tax risk
B10: Terminal growth | C10: Triangular | D10: 0.01 | E10: 0.02 | F10: 0.0275 | G10: Around long-run inflation
B11: CapEx (% of revenue) | C11: Triangular | D11: 0.12 | E11: 0.16 | F11: 0.22 | G11: Repowering and grid costs can overrun
B13: Fixed parameters
B14: Base revenue (€m) | D14: 145
B15: D&A (% of revenue) | D15: 0.13
B16: Change in NWC (% of incremental revenue) | D16: 0.03
B17: Net debt (€m) | D17: 185
B18: Shares outstanding (m) | D18: 25
B19: Market price (€) | D19: 11.5
B20: Forecast horizon (years) | D20: 5
B21: Minimum WACC minus terminal growth | D21: 0.015
B22: Correlation, growth and margin (Gaussian copula) | D22: 0.35
B23: WACC floor | D23: 0.055
B24: WACC cap | D24: 0.125
B26: Windfall-tax event (Windfall sheet)
B27: Ordinary tax: min | D27: 0.24
B28: Ordinary tax: mode | D28: 0.26
B29: Ordinary tax: max | D29: 0.28
B30: Probability of a windfall surcharge | D30: 0.25 | G30: Illustrative; chosen so the average tax matches the continuous model
B31: Surcharge if it happens (points) | D31: 0.09
B33: Triangular: min, most likely, max. Normal: mean and standard deviation. The guardrail keeps WACC at least 1.5 points above terminal growth.

Sheet DCF Base Case
B2: DCF base case
B3: Every driver at its most-likely value (the mode, or the mean for WACC)
B6: Revenue growth | C6: =Assumptions!E6 -> 0.09
B7: EBITDA margin | C7: =Assumptions!E7 -> 0.42
B8: WACC | C8: =Assumptions!D8 -> 0.085
B9: Tax rate | C9: =Assumptions!E9 -> 0.26
B10: Terminal growth | C10: =Assumptions!E10 -> 0.02
B11: CapEx (% of revenue) | C11: =Assumptions!E11 -> 0.16
B12: Discount rate used | C12: =MAX(C8,C10+Assumptions!$D$21) -> 0.085
B14: €m | C14: Year 0 | D14: Y1 | E14: Y2 | F14: Y3 | G14: Y4 | H14: Y5
B15: Revenue | C15: =Assumptions!$D$14 -> 145 | D15: =C15*(1+$C$6) -> 158.05 | E15: =D15*(1+$C$6) -> 172.2745 | F15: =E15*(1+$C$6) -> 187.7792 | G15: =F15*(1+$C$6) -> 204.67933 | H15: =G15*(1+$C$6) -> 223.10047
B16: EBITDA | D16: =D15*$C$7 -> 66.381 | E16: =E15*$C$7 -> 72.35529 | F16: =F15*$C$7 -> 78.867266 | G16: =G15*$C$7 -> 85.96532 | H16: =H15*$C$7 -> 93.702199
B17: D&A | D17: =D15*Assumptions!$D$15 -> 20.5465 | E17: =E15*Assumptions!$D$15 -> 22.395685 | F17: =F15*Assumptions!$D$15 -> 24.411297 | G17: =G15*Assumptions!$D$15 -> 26.608313 | H17: =H15*Assumptions!$D$15 -> 29.003062
B18: EBIT | D18: =D16-D17 -> 45.8345 | E18: =E16-E17 -> 49.959605 | F18: =F16-F17 -> 54.455969 | G18: =G16-G17 -> 59.357007 | H18: =H16-H17 -> 64.699137
B19: NOPAT | D19: =D18*(1-$C$9) -> 33.91753 | E19: =E18*(1-$C$9) -> 36.970108 | F19: =F18*(1-$C$9) -> 40.297417 | G19: =G18*(1-$C$9) -> 43.924185 | H19: =H18*(1-$C$9) -> 47.877362
B20: CapEx | D20: =D15*$C$11 -> 25.288 | E20: =E15*$C$11 -> 27.56392 | F20: =F15*$C$11 -> 30.044673 | G20: =G15*$C$11 -> 32.748693 | H20: =H15*$C$11 -> 35.696076
B21: Change in NWC | D21: =(D15-C15)*Assumptions!$D$16 -> 0.3915 | E21: =(E15-D15)*Assumptions!$D$16 -> 0.426735 | F21: =(F15-E15)*Assumptions!$D$16 -> 0.46514115 | G21: =(G15-F15)*Assumptions!$D$16 -> 0.50700385 | H21: =(H15-G15)*Assumptions!$D$16 -> 0.5526342
B22: Unlevered free cash flow | D22: =D19+D17-D20-D21 -> 28.78453 | E22: =E19+E17-E20-E21 -> 31.375138 | F22: =F19+F17-F20-F21 -> 34.1989 | G22: =G19+G17-G20-G21 -> 37.276801 | H22: =H19+H17-H20-H21 -> 40.631713
B23: Discount factor | D23: =1/(1+$C$12)^1 -> 0.92165899 | E23: =1/(1+$C$12)^2 -> 0.84945529 | F23: =1/(1+$C$12)^3 -> 0.7829081 | G23: =1/(1+$C$12)^4 -> 0.72157428 | H23: =1/(1+$C$12)^5 -> 0.66504542
B24: Present value | D24: =D22*D23 -> 26.529521 | E24: =E22*E23 -> 26.651777 | F24: =F22*F23 -> 26.774596 | G24: =G22*G23 -> 26.897981 | H24: =H22*H23 -> 27.021935
B26: Sum of present values | C26: =SUM(D24:H24) -> 133.87581
B27: Terminal value (Gordon) | C27: =H22*(1+C10)/(C12-C10) -> 637.60535
B28: Present value of terminal value | C28: =C27/(1+C12)^5 -> 424.03652
B29: Enterprise value | C29: =C26+C28 -> 557.91233
B30: Net debt | C30: =Assumptions!$D$17 -> 185
B31: Equity value | C31: =C29-C30 -> 372.91233
B32: Shares (m) | C32: =Assumptions!$D$18 -> 25
B34: Terminal value share of enterprise value | C34: =C28/C29 -> 0.76004149
B36: Value per share (€) | C36: =C31/C32 -> 14.916493

Sheet Random Draws
B2: Random draws
B3: Standard normals (z) and uniforms (u) from the Python engine, seed 113, rows 1 to 2,000 of 50,000
B5: Iter | C5: z growth | D5: z margin (indep.) | E5: z WACC | F5: u tax | G5: u terminal g | H5: u CapEx | I5: u windfall
B6: 1 | C6: 1.5938667 | D6: 0.66741473 | E6: -0.66569892 | F6: 0.96032825 | G6: 0.24608927 | H6: 0.85581691 | I6: 0.72772361
B7: 2 | C7: 0.52756548 | D7: -0.42350392 | E7: -0.97035347 | F7: 0.88039948 | G7: 0.97649384 | H7: 0.67930698 | I7: 0.95724377
B8: 3 | C8: -0.059307457 | D8: 0.38865075 | E8: -0.27277407 | F8: 0.46577074 | G8: 0.094711251 | H8: 0.89231492 | I8: 0.64704779
B9: 4 | C9: -2.2364523 | D9: 0.48400101 | E9: -0.20052701 | F9: 0.71788869 | G9: 0.17558595 | H9: 0.03651515 | I9: 0.68641593
B10: 5 | C10: 0.98821484 | D10: -1.2107974 | E10: 1.4362515 | F10: 0.14144392 | G10: 0.23746365 | H10: 0.53866168 | I10: 0.21607571
B11: 6 | C11: 2.4534825 | D11: -0.59854802 | E11: 1.4931354 | F11: 0.92815365 | G11: 0.47008725 | H11: 0.98265317 | I11: 0.35160849
B12: 7 | C12: 2.4825237 | D12: -0.52045022 | E12: 0.12507058 | F12: 0.10597644 | G12: 0.70662838 | H12: 0.43212914 | I12: 0.29721096
B13: 8 | C13: 0.49980802 | D13: -0.11660245 | E13: -1.2874882 | F13: 0.74621545 | G13: 0.10611424 | H13: 0.29021183 | I13: 0.7002352
B14: 9 | C14: -0.61342849 | D14: -0.35513788 | E14: 0.081235047 | F14: 0.56515354 | G14: 0.27714404 | H14: 0.5224274 | I14: 0.71710503
B15: 10 | C15: 0.92703185 | D15: 0.35756745 | E15: -1.1195795 | F15: 0.42489974 | G15: 0.85305217 | H15: 0.78734497 | I15: 0.83664131
B16: 11 | C16: -2.0145937 | D16: -0.52222551 | E16: -0.56213198 | F16: 0.47262645 | G16: 0.09429933 | H16: 0.11556574 | I16: 0.67160368
B17: 12 | C17: -0.48320167 | D17: 2.0462954 | E17: -0.80151721 | F17: 0.16611014 | G17: 0.13601654 | H17: 0.25379696 | I17: 0.80012186
... B2005: 2000 | C2005: -0.94585254 | D2005: 2.1333136 | E2005: -1.402944 | F2005: 0.042543054 | G2005: 0.59244045 | H2005: 0.13611643 | I2005: 0.21981453

Sheet Simulation
B2: Simulation
B3: One iteration per row. Drivers come from the random draws through each distribution; the valuation is the base-case DCF
B5: Iter | C5: u growth | D5: u margin | E5: Growth | F5: Margin | G5: WACC | H5: Tax | I5: Terminal g | J5: CapEx % | K5: Rate used | L5: FCF per € rev. | M5: UFCF Y1 | N5: UFCF Y2 | O5: UFCF Y3 | P5: UFCF Y4 | Q5: UFCF Y5 | R5: PV explicit | S5: Terminal value | T5: Enterprise value | U5: Value per share
B6: 1 | C6: =NORMSDIST('Random Draws'!C6) -> 0.94451706 | D6: =NORMSDIST(Assumptions!$D$22*'Random Draws'!C6+SQRT(1-Assumptions!$D$22^2)*'Random Draws'!D6) -> 0.88160611 | E6: =IF(C6<(Assumptions!$E$6-Assumptions!$D$6)/(Assumptions!$F$6-Assumptions!$D$6),Assumptions!$D$6+SQRT(C6*(Assumptions!$F$6-Assumptions!$D$6)*(Assumptions!$E$6-Assumptions!$D$6)),Assumptions!$F$6-SQRT((1-C6)*(Assumptions!$F$6-Assumptions!$D$6)*(Assumptions!$F$6-Assumptions!$E$6))) -> 0.12334423 | F6: =IF(D6<(Assumptions!$E$7-Assumptions!$D$7)/(Assumptions!$F$7-Assumptions!$D$7),Assumptions!$D$7+SQRT(D6*(Assumptions!$F$7-Assumptions!$D$7)*(Assumptions!$E$7-Assumptions!$D$7)),Assumptions!$F$7-SQRT((1-D6)*(Assumptions!$F$7-Assumptions!$D$7)*(Assumptions!$F$7-Assumptions!$E$7))) -> 0.43823821 | G6: =MIN(Assumptions!$D$24,MAX(Assumptions!$D$23,Assumptions!$D$8+Assumptions!$E$8*'Random Draws'!E6)) -> 0.077677312 | H6: =IF('Random Draws'!F6<(Assumptions!$E$9-Assumptions!$D$9)/(Assumptions!$F$9-Assumptions!$D$9),Assumptions!$D$9+SQRT('Random Draws'!F6*(Assumptions!$F$9-Assumptions!$D$9)*(Assumptions!$E$9-Assumptions!$D$9)),Assumptions!$F$9-SQRT((1-'Random Draws'!F6)*(Assumptions!$F$9-Assumptions!$D$9)*(Assumptions!$F$9-Assumptions!$E$9))) -> 0.33018207 | I6: =IF('Random Draws'!G6<(Assumptions!$E$10-Assumptions!$D$10)/(Assumptions!$F$10-Assumptions!$D$10),Assumptions!$D$10+SQRT('Random Draws'!G6*(Assumptions!$F$10-Assumptions!$D$10)*(Assumptions!$E$10-Assumptions!$D$10)),Assumptions!$F$10-SQRT((1-'Random Draws'!G6)*(Assumptions!$F$10-Assumptions!$D$10)*(Assumptions!$F$10-Assumptions!$E$10))) -> 0.01656244 | J6: =IF('Random Draws'!H6<(Assumptions!$E$11-Assumptions!$D$11)/(Assumptions!$F$11-Assumptions!$D$11),Assumptions!$D$11+SQRT('Random Draws'!H6*(Assumptions!$F$11-Assumptions!$D$11)*(Assumptions!$E$11-Assumptions!$D$11)),Assumptions!$F$11-SQRT((1-'Random Draws'!H6)*(Assumptions!$F$11-Assumptions!$D$11)*(Assumptions!$F$11-Assumptions!$E$11))) -> 0.19058744 | K6: =MAX(G6,I6+Assumptions!$D$21) -> 0.077677312 | L6: =(F6-Assumptions!$D$15)*(1-H6)+Assumptions!$D$15-J6 -> 0.14587604 | M6: =Assumptions!$D$14*(1+E6)^1*L6-Assumptions!$D$14*(1+E6)^0*E6*Assumptions!$D$16 -> 23.224458 | N6: =Assumptions!$D$14*(1+E6)^2*L6-Assumptions!$D$14*(1+E6)^1*E6*Assumptions!$D$16 -> 26.089061 | O6: =Assumptions!$D$14*(1+E6)^3*L6-Assumptions!$D$14*(1+E6)^2*E6*Assumptions!$D$16 -> 29.306996 | P6: =Assumptions!$D$14*(1+E6)^4*L6-Assumptions!$D$14*(1+E6)^3*E6*Assumptions!$D$16 -> 32.921845 | Q6: =Assumptions!$D$14*(1+E6)^5*L6-Assumptions!$D$14*(1+E6)^4*E6*Assumptions!$D$16 -> 36.982565 | R6: =M6/(1+K6)+N6/(1+K6)^2+O6/(1+K6)^3+P6/(1+K6)^4+Q6/(1+K6)^5 -> 117.2797 | S6: =Q6*(1+I6)/(K6-I6) -> 615.15446 | T6: =R6+S6/(1+K6)^5 -> 540.47466 | U6: =(T6-Assumptions!$D$17)/Assumptions!$D$18 -> 14.218986
B7: 2 | C7: =NORMSDIST('Random Draws'!C7) -> 0.70109952 | D7: =NORMSDIST(Assumptions!$D$22*'Random Draws'!C7+SQRT(1-Assumptions!$D$22^2)*'Random Draws'!D7) -> 0.4160265 | E7: =IF(C7<(Assumptions!$E$6-Assumptions!$D$6)/(Assumptions!$F$6-Assumptions!$D$6),Assumptions!$D$6+SQRT(C7*(Assumptions!$F$6-Assumptions!$D$6)*(Assumptions!$E$6-Assumptions!$D$6)),Assumptions!$F$6-SQRT((1-C7)*(Assumptions!$F$6-Assumptions!$D$6)*(Assumptions!$F$6-Assumptions!$E$6))) -> 0.10134121 | F7: =IF(D7<(Assumptions!$E$7-Assumptions!$D$7)/(Assumptions!$F$7-Assumptions!$D$7),Assumptions!$D$7+SQRT(D7*(Assumptions!$F$7-Assumptions!$D$7)*(Assumptions!$E$7-Assumptions!$D$7)),Assumptions!$F$7-SQRT((1-D7)*(Assumptions!$F$7-Assumptions!$D$7)*(Assumptions!$F$7-Assumptions!$E$7))) -> 0.40996158 | G7: =MIN(Assumptions!$D$24,MAX(Assumptions!$D$23,Assumptions!$D$8+Assumptions!$E$8*'Random Draws'!E7)) -> 0.074326112 | H7: =IF('Random Draws'!F7<(Assumptions!$E$9-Assumptions!$D$9)/(Assumptions!$F$9-Assumptions!$D$9),Assumptions!$D$9+SQRT('Random Draws'!F7*(Assumptions!$F$9-Assumptions!$D$9)*(Assumptions!$E$9-Assumptions!$D$9)),Assumptions!$F$9-SQRT((1-'Random Draws'!F7)*(Assumptions!$F$9-Assumptions!$D$9)*(Assumptions!$F$9-Assumptions!$E$9))) -> 0.31559004 | I7: =IF('Random Draws'!G7<(Assumptions!$E$10-Assumptions!$D$10)/(Assumptions!$F$10-Assumptions!$D$10),Assumptions!$D$10+SQRT('Random Draws'!G7*(Assumptions!$F$10-Assumptions!$D$10)*(Assumptions!$E$10-Assumptions!$D$10)),Assumptions!$F$10-SQRT((1-'Random Draws'!G7)*(Assumptions!$F$10-Assumptions!$D$10)*(Assumptions!$F$10-Assumptions!$E$10))) -> 0.025743531 | J7: =IF('Random Draws'!H7<(Assumptions!$E$11-Assumptions!$D$11)/(Assumptions!$F$11-Assumptions!$D$11),Assumptions!$D$11+SQRT('Random Draws'!H7*(Assumptions!$F$11-Assumptions!$D$11)*(Assumptions!$E$11-Assumptions!$D$11)),Assumptions!$F$11-SQRT((1-'Random Draws'!H7)*(Assumptions!$F$11-Assumptions!$D$11)*(Assumptions!$F$11-Assumptions!$E$11))) -> 0.17613477 | K7: =MAX(G7,I7+Assumptions!$D$21) -> 0.074326112 | L7: =(F7-Assumptions!$D$15)*(1-H7)+Assumptions!$D$15-J7 -> 0.14547372 | M7: =Assumptions!$D$14*(1+E7)^1*L7-Assumptions!$D$14*(1+E7)^0*E7*Assumptions!$D$16 -> 22.790515 | N7: =Assumptions!$D$14*(1+E7)^2*L7-Assumptions!$D$14*(1+E7)^1*E7*Assumptions!$D$16 -> 25.100133 | O7: =Assumptions!$D$14*(1+E7)^3*L7-Assumptions!$D$14*(1+E7)^2*E7*Assumptions!$D$16 -> 27.64381 | P7: =Assumptions!$D$14*(1+E7)^4*L7-Assumptions!$D$14*(1+E7)^3*E7*Assumptions!$D$16 -> 30.445268 | Q7: =Assumptions!$D$14*(1+E7)^5*L7-Assumptions!$D$14*(1+E7)^4*E7*Assumptions!$D$16 -> 33.530628 | R7: =M7/(1+K7)+N7/(1+K7)^2+O7/(1+K7)^3+P7/(1+K7)^4+Q7/(1+K7)^5 -> 111.53915 | S7: =Q7*(1+I7)/(K7-I7) -> 707.9456 | T7: =R7+S7/(1+K7)^5 -> 606.21332 | U7: =(T7-Assumptions!$D$17)/Assumptions!$D$18 -> 16.848533
B8: 3 | C8: =NORMSDIST('Random Draws'!C8) -> 0.47635361 | D8: =NORMSDIST(Assumptions!$D$22*'Random Draws'!C8+SQRT(1-Assumptions!$D$22^2)*'Random Draws'!D8) -> 0.63431769 | E8: =IF(C8<(Assumptions!$E$6-Assumptions!$D$6)/(Assumptions!$F$6-Assumptions!$D$6),Assumptions!$D$6+SQRT(C8*(Assumptions!$F$6-Assumptions!$D$6)*(Assumptions!$E$6-Assumptions!$D$6)),Assumptions!$F$6-SQRT((1-C8)*(Assumptions!$F$6-Assumptions!$D$6)*(Assumptions!$F$6-Assumptions!$E$6))) -> 0.088803361 | F8: =IF(D8<(Assumptions!$E$7-Assumptions!$D$7)/(Assumptions!$F$7-Assumptions!$D$7),Assumptions!$D$7+SQRT(D8*(Assumptions!$F$7-Assumptions!$D$7)*(Assumptions!$E$7-Assumptions!$D$7)),Assumptions!$F$7-SQRT((1-D8)*(Assumptions!$F$7-Assumptions!$D$7)*(Assumptions!$F$7-Assumptions!$E$7))) -> 0.42175436 | G8: =MIN(Assumptions!$D$24,MAX(Assumptions!$D$23,Assumptions!$D$8+Assumptions!$E$8*'Random Draws'!E8)) -> 0.081999485 | H8: =IF('Random Draws'!F8<(Assumptions!$E$9-Assumptions!$D$9)/(Assumptions!$F$9-Assumptions!$D$9),Assumptions!$D$9+SQRT('Random Draws'!F8*(Assumptions!$F$9-Assumptions!$D$9)*(Assumptions!$E$9-Assumptions!$D$9)),Assumptions!$F$9-SQRT((1-'Random Draws'!F8)*(Assumptions!$F$9-Assumptions!$D$9)*(Assumptions!$F$9-Assumptions!$E$9))) -> 0.27727538 | I8: =IF('Random Draws'!G8<(Assumptions!$E$10-Assumptions!$D$10)/(Assumptions!$F$10-Assumptions!$D$10),Assumptions!$D$10+SQRT('Random Draws'!G8*(Assumptions!$F$10-Assumptions!$D$10)*(Assumptions!$E$10-Assumptions!$D$10)),Assumptions!$F$10-SQRT((1-'Random Draws'!G8)*(Assumptions!$F$10-Assumptions!$D$10)*(Assumptions!$F$10-Assumptions!$E$10))) -> 0.014071175 | J8: =IF('Random Draws'!H8<(Assumptions!$E$11-Assumptions!$D$11)/(Assumptions!$F$11-Assumptions!$D$11),Assumptions!$D$11+SQRT('Random Draws'!H8*(Assumptions!$F$11-Assumptions!$D$11)*(Assumptions!$E$11-Assumptions!$D$11)),Assumptions!$F$11-SQRT((1-'Random Draws'!H8)*(Assumptions!$F$11-Assumptions!$D$11)*(Assumptions!$F$11-Assumptions!$E$11))) -> 0.1945813 | K8: =MAX(G8,I8+Assumptions!$D$21) -> 0.081999485 | L8: =(F8-Assumptions!$D$15)*(1-H8)+Assumptions!$D$15-J8 -> 0.14627676 | M8: =Assumptions!$D$14*(1+E8)^1*L8-Assumptions!$D$14*(1+E8)^0*E8*Assumptions!$D$16 -> 22.707366 | N8: =Assumptions!$D$14*(1+E8)^2*L8-Assumptions!$D$14*(1+E8)^1*E8*Assumptions!$D$16 -> 24.723857 | O8: =Assumptions!$D$14*(1+E8)^3*L8-Assumptions!$D$14*(1+E8)^2*E8*Assumptions!$D$16 -> 26.919418 | P8: =Assumptions!$D$14*(1+E8)^4*L8-Assumptions!$D$14*(1+E8)^3*E8*Assumptions!$D$16 -> 29.309953 | Q8: =Assumptions!$D$14*(1+E8)^5*L8-Assumptions!$D$14*(1+E8)^4*E8*Assumptions!$D$16 -> 31.912775 | R8: =M8/(1+K8)+N8/(1+K8)^2+O8/(1+K8)^3+P8/(1+K8)^4+Q8/(1+K8)^5 -> 106.26043 | S8: =Q8*(1+I8)/(K8-I8) -> 476.41146 | T8: =R8+S8/(1+K8)^5 -> 427.51324 | U8: =(T8-Assumptions!$D$17)/Assumptions!$D$18 -> 9.7005296
B9: 4 | C9: =NORMSDIST('Random Draws'!C9) -> 0.012661079 | D9: =NORMSDIST(Assumptions!$D$22*'Random Draws'!C9+SQRT(1-Assumptions!$D$22^2)*'Random Draws'!D9) -> 0.37093783 | E9: =IF(C9<(Assumptions!$E$6-Assumptions!$D$6)/(Assumptions!$F$6-Assumptions!$D$6),Assumptions!$D$6+SQRT(C9*(Assumptions!$F$6-Assumptions!$D$6)*(Assumptions!$E$6-Assumptions!$D$6)),Assumptions!$F$6-SQRT((1-C9)*(Assumptions!$F$6-Assumptions!$D$6)*(Assumptions!$F$6-Assumptions!$E$6))) -> 0.047956469 | F9: =IF(D9<(Assumptions!$E$7-Assumptions!$D$7)/(Assumptions!$F$7-Assumptions!$D$7),Assumptions!$D$7+SQRT(D9*(Assumptions!$F$7-Assumptions!$D$7)*(Assumptions!$E$7-Assumptions!$D$7)),Assumptions!$F$7-SQRT((1-D9)*(Assumptions!$F$7-Assumptions!$D$7)*(Assumptions!$F$7-Assumptions!$E$7))) -> 0.40717655 | G9: =MIN(Assumptions!$D$24,MAX(Assumptions!$D$23,Assumptions!$D$8+Assumptions!$E$8*'Random Draws'!E9)) -> 0.082794203 | H9: =IF('Random Draws'!F9<(Assumptions!$E$9-Assumptions!$D$9)/(Assumptions!$F$9-Assumptions!$D$9),Assumptions!$D$9+SQRT('Random Draws'!F9*(Assumptions!$F$9-Assumptions!$D$9)*(Assumptions!$E$9-Assumptions!$D$9)),Assumptions!$F$9-SQRT((1-'Random Draws'!F9)*(Assumptions!$F$9-Assumptions!$D$9)*(Assumptions!$F$9-Assumptions!$E$9))) -> 0.29715209 | I9: =IF('Random Draws'!G9<(Assumptions!$E$10-Assumptions!$D$10)/(Assumptions!$F$10-Assumptions!$D$10),Assumptions!$D$10+SQRT('Random Draws'!G9*(Assumptions!$F$10-Assumptions!$D$10)*(Assumptions!$E$10-Assumptions!$D$10)),Assumptions!$F$10-SQRT((1-'Random Draws'!G9)*(Assumptions!$F$10-Assumptions!$D$10)*(Assumptions!$F$10-Assumptions!$E$10))) -> 0.015543243 | J9: =IF('Random Draws'!H9<(Assumptions!$E$11-Assumptions!$D$11)/(Assumptions!$F$11-Assumptions!$D$11),Assumptions!$D$11+SQRT('Random Draws'!H9*(Assumptions!$F$11-Assumptions!$D$11)*(Assumptions!$E$11-Assumptions!$D$11)),Assumptions!$F$11-SQRT((1-'Random Draws'!H9)*(Assumptions!$F$11-Assumptions!$D$11)*(Assumptions!$F$11-Assumptions!$E$11))) -> 0.13208555 | K9: =MAX(G9,I9+Assumptions!$D$21) -> 0.082794203 | L9: =(F9-Assumptions!$D$15)*(1-H9)+Assumptions!$D$15-J9 -> 0.19272741 | M9: =Assumptions!$D$14*(1+E9)^1*L9-Assumptions!$D$14*(1+E9)^0*E9*Assumptions!$D$16 -> 29.07703 | N9: =Assumptions!$D$14*(1+E9)^2*L9-Assumptions!$D$14*(1+E9)^1*E9*Assumptions!$D$16 -> 30.471461 | O9: =Assumptions!$D$14*(1+E9)^3*L9-Assumptions!$D$14*(1+E9)^2*E9*Assumptions!$D$16 -> 31.932765 | P9: =Assumptions!$D$14*(1+E9)^4*L9-Assumptions!$D$14*(1+E9)^3*E9*Assumptions!$D$16 -> 33.464148 | Q9: =Assumptions!$D$14*(1+E9)^5*L9-Assumptions!$D$14*(1+E9)^4*E9*Assumptions!$D$16 -> 35.06897 | R9: =M9/(1+K9)+N9/(1+K9)^2+O9/(1+K9)^3+P9/(1+K9)^4+Q9/(1+K9)^5 -> 125.90214 | S9: =Q9*(1+I9)/(K9-I9) -> 529.56947 | T9: =R9+S9/(1+K9)^5 -> 481.69181 | U9: =(T9-Assumptions!$D$17)/Assumptions!$D$18 -> 11.867673
B10: 5 | C10: =NORMSDIST('Random Draws'!C10) -> 0.83847628 | D10: =NORMSDIST(Assumptions!$D$22*'Random Draws'!C10+SQRT(1-Assumptions!$D$22^2)*'Random Draws'!D10) -> 0.21524924 | E10: =IF(C10<(Assumptions!$E$6-Assumptions!$D$6)/(Assumptions!$F$6-Assumptions!$D$6),Assumptions!$D$6+SQRT(C10*(Assumptions!$F$6-Assumptions!$D$6)*(Assumptions!$E$6-Assumptions!$D$6)),Assumptions!$F$6-SQRT((1-C10)*(Assumptions!$F$6-Assumptions!$D$6)*(Assumptions!$F$6-Assumptions!$E$6))) -> 0.11158137 | F10: =IF(D10<(Assumptions!$E$7-Assumptions!$D$7)/(Assumptions!$F$7-Assumptions!$D$7),Assumptions!$D$7+SQRT(D10*(Assumptions!$F$7-Assumptions!$D$7)*(Assumptions!$E$7-Assumptions!$D$7)),Assumptions!$F$7-SQRT((1-D10)*(Assumptions!$F$7-Assumptions!$D$7)*(Assumptions!$F$7-Assumptions!$E$7))) -> 0.39593738 | G10: =MIN(Assumptions!$D$24,MAX(Assumptions!$D$23,Assumptions!$D$8+Assumptions!$E$8*'Random Draws'!E10)) -> 0.10079877 | H10: =IF('Random Draws'!F10<(Assumptions!$E$9-Assumptions!$D$9)/(Assumptions!$F$9-Assumptions!$D$9),Assumptions!$D$9+SQRT('Random Draws'!F10*(Assumptions!$F$9-Assumptions!$D$9)*(Assumptions!$E$9-Assumptions!$D$9)),Assumptions!$F$9-SQRT((1-'Random Draws'!F10)*(Assumptions!$F$9-Assumptions!$D$9)*(Assumptions!$F$9-Assumptions!$E$9))) -> 0.2576402 | I10: =IF('Random Draws'!G10<(Assumptions!$E$10-Assumptions!$D$10)/(Assumptions!$F$10-Assumptions!$D$10),Assumptions!$D$10+SQRT('Random Draws'!G10*(Assumptions!$F$10-Assumptions!$D$10)*(Assumptions!$E$10-Assumptions!$D$10)),Assumptions!$F$10-SQRT((1-'Random Draws'!G10)*(Assumptions!$F$10-Assumptions!$D$10)*(Assumptions!$F$10-Assumptions!$E$10))) -> 0.016446405 | J10: =IF('Random Draws'!H10<(Assumptions!$E$11-Assumptions!$D$11)/(Assumptions!$F$11-Assumptions!$D$11),Assumptions!$D$11+SQRT('Random Draws'!H10*(Assumptions!$F$11-Assumptions!$D$11)*(Assumptions!$E$11-Assumptions!$D$11)),Assumptions!$F$11-SQRT((1-'Random Draws'!H10)*(Assumptions!$F$11-Assumptions!$D$11)*(Assumptions!$F$11-Assumptions!$E$11))) -> 0.16738793 | K10: =MAX(G10,I10+Assumptions!$D$21) -> 0.10079877 | L10: =(F10-Assumptions!$D$15)*(1-H10)+Assumptions!$D$15-J10 -> 0.16003329 | M10: =Assumptions!$D$14*(1+E10)^1*L10-Assumptions!$D$14*(1+E10)^0*E10*Assumptions!$D$16 -> 25.308675 | N10: =Assumptions!$D$14*(1+E10)^2*L10-Assumptions!$D$14*(1+E10)^1*E10*Assumptions!$D$16 -> 28.132651 | O10: =Assumptions!$D$14*(1+E10)^3*L10-Assumptions!$D$14*(1+E10)^2*E10*Assumptions!$D$16 -> 31.271731 | P10: =Assumptions!$D$14*(1+E10)^4*L10-Assumptions!$D$14*(1+E10)^3*E10*Assumptions!$D$16 -> 34.761074 | Q10: =Assumptions!$D$14*(1+E10)^5*L10-Assumptions!$D$14*(1+E10)^4*E10*Assumptions!$D$16 -> 38.639762 | R10: =M10/(1+K10)+N10/(1+K10)^2+O10/(1+K10)^3+P10/(1+K10)^4+Q10/(1+K10)^5 -> 117.23017 | S10: =Q10*(1+I10)/(K10-I10) -> 465.60934 | T10: =R10+S10/(1+K10)^5 -> 405.28954 | U10: =(T10-Assumptions!$D$17)/Assumptions!$D$18 -> 8.8115818
B11: 6 | C11: =NORMSDIST('Random Draws'!C11) -> 0.99292598 | D11: =NORMSDIST(Assumptions!$D$22*'Random Draws'!C11+SQRT(1-Assumptions!$D$22^2)*'Random Draws'!D11) -> 0.61715956 | E11: =IF(C11<(Assumptions!$E$6-Assumptions!$D$6)/(Assumptions!$F$6-Assumptions!$D$6),Assumptions!$D$6+SQRT(C11*(Assumptions!$F$6-Assumptions!$D$6)*(Assumptions!$E$6-Assumptions!$D$6)),Assumptions!$F$6-SQRT((1-C11)*(Assumptions!$F$6-Assumptions!$D$6)*(Assumptions!$F$6-Assumptions!$E$6))) -> 0.13405272 | F11: =IF(D11<(Assumptions!$E$7-Assumptions!$D$7)/(Assumptions!$F$7-Assumptions!$D$7),Assumptions!$D$7+SQRT(D11*(Assumptions!$F$7-Assumptions!$D$7)*(Assumptions!$E$7-Assumptions!$D$7)),Assumptions!$F$7-SQRT((1-D11)*(Assumptions!$F$7-Assumptions!$D$7)*(Assumptions!$F$7-Assumptions!$E$7))) -> 0.42086738 | G11: =MIN(Assumptions!$D$24,MAX(Assumptions!$D$23,Assumptions!$D$8+Assumptions!$E$8*'Random Draws'!E11)) -> 0.10142449 | H11: =IF('Random Draws'!F11<(Assumptions!$E$9-Assumptions!$D$9)/(Assumptions!$F$9-Assumptions!$D$9),Assumptions!$D$9+SQRT('Random Draws'!F11*(Assumptions!$F$9-Assumptions!$D$9)*(Assumptions!$E$9-Assumptions!$D$9)),Assumptions!$F$9-SQRT((1-'Random Draws'!F11)*(Assumptions!$F$9-Assumptions!$D$9)*(Assumptions!$F$9-Assumptions!$E$9))) -> 0.32333019 | I11: =IF('Random Draws'!G11<(Assumptions!$E$10-Assumptions!$D$10)/(Assumptions!$F$10-Assumptions!$D$10),Assumptions!$D$10+SQRT('Random Draws'!G11*(Assumptions!$F$10-Assumptions!$D$10)*(Assumptions!$E$10-Assumptions!$D$10)),Assumptions!$F$10-SQRT((1-'Random Draws'!G11)*(Assumptions!$F$10-Assumptions!$D$10)*(Assumptions!$F$10-Assumptions!$E$10))) -> 0.01907002 | J11: =IF('Random Draws'!H11<(Assumptions!$E$11-Assumptions!$D$11)/(Assumptions!$F$11-Assumptions!$D$11),Assumptions!$D$11+SQRT('Random Draws'!H11*(Assumptions!$F$11-Assumptions!$D$11)*(Assumptions!$E$11-Assumptions!$D$11)),Assumptions!$F$11-SQRT((1-'Random Draws'!H11)*(Assumptions!$F$11-Assumptions!$D$11)*(Assumptions!$F$11-Assumptions!$E$11))) -> 0.20979799 | K11: =MAX(G11,I11+Assumptions!$D$21) -> 0.10142449 | L11: =(F11-Assumptions!$D$15)*(1-H11)+Assumptions!$D$15-J11 -> 0.11702319 | M11: =Assumptions!$D$14*(1+E11)^1*L11-Assumptions!$D$14*(1+E11)^0*E11*Assumptions!$D$16 -> 18.659888 | N11: =Assumptions!$D$14*(1+E11)^2*L11-Assumptions!$D$14*(1+E11)^1*E11*Assumptions!$D$16 -> 21.161296 | O11: =Assumptions!$D$14*(1+E11)^3*L11-Assumptions!$D$14*(1+E11)^2*E11*Assumptions!$D$16 -> 23.998026 | P11: =Assumptions!$D$14*(1+E11)^4*L11-Assumptions!$D$14*(1+E11)^3*E11*Assumptions!$D$16 -> 27.215027 | Q11: =Assumptions!$D$14*(1+E11)^5*L11-Assumptions!$D$14*(1+E11)^4*E11*Assumptions!$D$16 -> 30.863275 | R11: =M11/(1+K11)+N11/(1+K11)^2+O11/(1+K11)^3+P11/(1+K11)^4+Q11/(1+K11)^5 -> 89.877585 | S11: =Q11*(1+I11)/(K11-I11) -> 381.90809 | T11: =R11+S11/(1+K11)^5 -> 325.48297 | U11: =(T11-Assumptions!$D$17)/Assumptions!$D$18 -> 5.619319
B12: 7 | C12: =NORMSDIST('Random Draws'!C12) -> 0.99347723 | D12: =NORMSDIST(Assumptions!$D$22*'Random Draws'!C12+SQRT(1-Assumptions!$D$22^2)*'Random Draws'!D12) -> 0.64852886 | E12: =IF(C12<(Assumptions!$E$6-Assumptions!$D$6)/(Assumptions!$F$6-Assumptions!$D$6),Assumptions!$D$6+SQRT(C12*(Assumptions!$F$6-Assumptions!$D$6)*(Assumptions!$E$6-Assumptions!$D$6)),Assumptions!$F$6-SQRT((1-C12)*(Assumptions!$F$6-Assumptions!$D$6)*(Assumptions!$F$6-Assumptions!$E$6))) -> 0.13428915 | F12: =IF(D12<(Assumptions!$E$7-Assumptions!$D$7)/(Assumptions!$F$7-Assumptions!$D$7),Assumptions!$D$7+SQRT(D12*(Assumptions!$F$7-Assumptions!$D$7)*(Assumptions!$E$7-Assumptions!$D$7)),Assumptions!$F$7-SQRT((1-D12)*(Assumptions!$F$7-Assumptions!$D$7)*(Assumptions!$F$7-Assumptions!$E$7))) -> 0.42250487 | G12: =MIN(Assumptions!$D$24,MAX(Assumptions!$D$23,Assumptions!$D$8+Assumptions!$E$8*'Random Draws'!E12)) -> 0.086375776 | H12: =IF('Random Draws'!F12<(Assumptions!$E$9-Assumptions!$D$9)/(Assumptions!$F$9-Assumptions!$D$9),Assumptions!$D$9+SQRT('Random Draws'!F12*(Assumptions!$F$9-Assumptions!$D$9)*(Assumptions!$E$9-Assumptions!$D$9)),Assumptions!$F$9-SQRT((1-'Random Draws'!F12)*(Assumptions!$F$9-Assumptions!$D$9)*(Assumptions!$F$9-Assumptions!$E$9))) -> 0.25526919 | I12: =IF('Random Draws'!G12<(Assumptions!$E$10-Assumptions!$D$10)/(Assumptions!$F$10-Assumptions!$D$10),Assumptions!$D$10+SQRT('Random Draws'!G12*(Assumptions!$F$10-Assumptions!$D$10)*(Assumptions!$E$10-Assumptions!$D$10)),Assumptions!$F$10-SQRT((1-'Random Draws'!G12)*(Assumptions!$F$10-Assumptions!$D$10)*(Assumptions!$F$10-Assumptions!$E$10))) -> 0.021294758 | J12: =IF('Random Draws'!H12<(Assumptions!$E$11-Assumptions!$D$11)/(Assumptions!$F$11-Assumptions!$D$11),Assumptions!$D$11+SQRT('Random Draws'!H12*(Assumptions!$F$11-Assumptions!$D$11)*(Assumptions!$E$11-Assumptions!$D$11)),Assumptions!$F$11-SQRT((1-'Random Draws'!H12)*(Assumptions!$F$11-Assumptions!$D$11)*(Assumptions!$F$11-Assumptions!$E$11))) -> 0.16162856 | K12: =MAX(G12,I12+Assumptions!$D$21) -> 0.086375776 | L12: =(F12-Assumptions!$D$15)*(1-H12)+Assumptions!$D$15-J12 -> 0.18620883 | M12: =Assumptions!$D$14*(1+E12)^1*L12-Assumptions!$D$14*(1+E12)^0*E12*Assumptions!$D$16 -> 30.041967 | N12: =Assumptions!$D$14*(1+E12)^2*L12-Assumptions!$D$14*(1+E12)^1*E12*Assumptions!$D$16 -> 34.076278 | O12: =Assumptions!$D$14*(1+E12)^3*L12-Assumptions!$D$14*(1+E12)^2*E12*Assumptions!$D$16 -> 38.652352 | P12: =Assumptions!$D$14*(1+E12)^4*L12-Assumptions!$D$14*(1+E12)^3*E12*Assumptions!$D$16 -> 43.842943 | Q12: =Assumptions!$D$14*(1+E12)^5*L12-Assumptions!$D$14*(1+E12)^4*E12*Assumptions!$D$16 -> 49.730575 | R12: =M12/(1+K12)+N12/(1+K12)^2+O12/(1+K12)^3+P12/(1+K12)^4+Q12/(1+K12)^5 -> 151.013 | S12: =Q12*(1+I12)/(K12-I12) -> 780.40536 | T12: =R12+S12/(1+K12)^5 -> 666.74001 | U12: =(T12-Assumptions!$D$17)/Assumptions!$D$18 -> 19.2696
B13: 8 | C13: =NORMSDIST('Random Draws'!C13) -> 0.69139487 | D13: =NORMSDIST(Assumptions!$D$22*'Random Draws'!C13+SQRT(1-Assumptions!$D$22^2)*'Random Draws'!D13) -> 0.52619385 | E13: =IF(C13<(Assumptions!$E$6-Assumptions!$D$6)/(Assumptions!$F$6-Assumptions!$D$6),Assumptions!$D$6+SQRT(C13*(Assumptions!$F$6-Assumptions!$D$6)*(Assumptions!$E$6-Assumptions!$D$6)),Assumptions!$F$6-SQRT((1-C13)*(Assumptions!$F$6-Assumptions!$D$6)*(Assumptions!$F$6-Assumptions!$E$6))) -> 0.10071863 | F13: =IF(D13<(Assumptions!$E$7-Assumptions!$D$7)/(Assumptions!$F$7-Assumptions!$D$7),Assumptions!$D$7+SQRT(D13*(Assumptions!$F$7-Assumptions!$D$7)*(Assumptions!$E$7-Assumptions!$D$7)),Assumptions!$F$7-SQRT((1-D13)*(Assumptions!$F$7-Assumptions!$D$7)*(Assumptions!$F$7-Assumptions!$E$7))) -> 0.41618864 | G13: =MIN(Assumptions!$D$24,MAX(Assumptions!$D$23,Assumptions!$D$8+Assumptions!$E$8*'Random Draws'!E13)) -> 0.07083763 | H13: =IF('Random Draws'!F13<(Assumptions!$E$9-Assumptions!$D$9)/(Assumptions!$F$9-Assumptions!$D$9),Assumptions!$D$9+SQRT('Random Draws'!F13*(Assumptions!$F$9-Assumptions!$D$9)*(Assumptions!$E$9-Assumptions!$D$9)),Assumptions!$F$9-SQRT((1-'Random Draws'!F13)*(Assumptions!$F$9-Assumptions!$D$9)*(Assumptions!$F$9-Assumptions!$E$9))) -> 0.29987548 | I13: =IF('Random Draws'!G13<(Assumptions!$E$10-Assumptions!$D$10)/(Assumptions!$F$10-Assumptions!$D$10),Assumptions!$D$10+SQRT('Random Draws'!G13*(Assumptions!$F$10-Assumptions!$D$10)*(Assumptions!$E$10-Assumptions!$D$10)),Assumptions!$F$10-SQRT((1-'Random Draws'!G13)*(Assumptions!$F$10-Assumptions!$D$10)*(Assumptions!$F$10-Assumptions!$E$10))) -> 0.014309291 | J13: =IF('Random Draws'!H13<(Assumptions!$E$11-Assumptions!$D$11)/(Assumptions!$F$11-Assumptions!$D$11),Assumptions!$D$11+SQRT('Random Draws'!H13*(Assumptions!$F$11-Assumptions!$D$11)*(Assumptions!$E$11-Assumptions!$D$11)),Assumptions!$F$11-SQRT((1-'Random Draws'!H13)*(Assumptions!$F$11-Assumptions!$D$11)*(Assumptions!$F$11-Assumptions!$E$11))) -> 0.15407121 | K13: =MAX(G13,I13+Assumptions!$D$21) -> 0.07083763 | L13: =(F13-Assumptions!$D$15)*(1-H13)+Assumptions!$D$15-J13 -> 0.17629647 | M13: =Assumptions!$D$14*(1+E13)^1*L13-Assumptions!$D$14*(1+E13)^0*E13*Assumptions!$D$16 -> 27.699532 | N13: =Assumptions!$D$14*(1+E13)^2*L13-Assumptions!$D$14*(1+E13)^1*E13*Assumptions!$D$16 -> 30.489391 | O13: =Assumptions!$D$14*(1+E13)^3*L13-Assumptions!$D$14*(1+E13)^2*E13*Assumptions!$D$16 -> 33.560241 | P13: =Assumptions!$D$14*(1+E13)^4*L13-Assumptions!$D$14*(1+E13)^3*E13*Assumptions!$D$16 -> 36.940382 | Q13: =Assumptions!$D$14*(1+E13)^5*L13-Assumptions!$D$14*(1+E13)^4*E13*Assumptions!$D$16 -> 40.660967 | R13: =M13/(1+K13)+N13/(1+K13)^2+O13/(1+K13)^3+P13/(1+K13)^4+Q13/(1+K13)^5 -> 136.75812 | S13: =Q13*(1+I13)/(K13-I13) -> 729.59506 | T13: =R13+S13/(1+K13)^5 -> 654.91797 | U13: =(T13-Assumptions!$D$17)/Assumptions!$D$18 -> 18.796719
B14: 9 | C14: =NORMSDIST('Random Draws'!C14) -> 0.26979653 | D14: =NORMSDIST(Assumptions!$D$22*'Random Draws'!C14+SQRT(1-Assumptions!$D$22^2)*'Random Draws'!D14) -> 0.29206047 | E14: =IF(C14<(Assumptions!$E$6-Assumptions!$D$6)/(Assumptions!$F$6-Assumptions!$D$6),Assumptions!$D$6+SQRT(C14*(Assumptions!$F$6-Assumptions!$D$6)*(Assumptions!$E$6-Assumptions!$D$6)),Assumptions!$F$6-SQRT((1-C14)*(Assumptions!$F$6-Assumptions!$D$6)*(Assumptions!$F$6-Assumptions!$E$6))) -> 0.076728499 | F14: =IF(D14<(Assumptions!$E$7-Assumptions!$D$7)/(Assumptions!$F$7-Assumptions!$D$7),Assumptions!$D$7+SQRT(D14*(Assumptions!$F$7-Assumptions!$D$7)*(Assumptions!$E$7-Assumptions!$D$7)),Assumptions!$F$7-SQRT((1-D14)*(Assumptions!$F$7-Assumptions!$D$7)*(Assumptions!$F$7-Assumptions!$E$7))) -> 0.40186123 | G14: =MIN(Assumptions!$D$24,MAX(Assumptions!$D$23,Assumptions!$D$8+Assumptions!$E$8*'Random Draws'!E14)) -> 0.085893586 | H14: =IF('Random Draws'!F14<(Assumptions!$E$9-Assumptions!$D$9)/(Assumptions!$F$9-Assumptions!$D$9),Assumptions!$D$9+SQRT('Random Draws'!F14*(Assumptions!$F$9-Assumptions!$D$9)*(Assumptions!$E$9-Assumptions!$D$9)),Assumptions!$F$9-SQRT((1-'Random Draws'!F14)*(Assumptions!$F$9-Assumptions!$D$9)*(Assumptions!$F$9-Assumptions!$E$9))) -> 0.28438765 | I14: =IF('Random Draws'!G14<(Assumptions!$E$10-Assumptions!$D$10)/(Assumptions!$F$10-Assumptions!$D$10),Assumptions!$D$10+SQRT('Random Draws'!G14*(Assumptions!$F$10-Assumptions!$D$10)*(Assumptions!$E$10-Assumptions!$D$10)),Assumptions!$F$10-SQRT((1-'Random Draws'!G14)*(Assumptions!$F$10-Assumptions!$D$10)*(Assumptions!$F$10-Assumptions!$E$10))) -> 0.016964209 | J14: =IF('Random Draws'!H14<(Assumptions!$E$11-Assumptions!$D$11)/(Assumptions!$F$11-Assumptions!$D$11),Assumptions!$D$11+SQRT('Random Draws'!H14*(Assumptions!$F$11-Assumptions!$D$11)*(Assumptions!$E$11-Assumptions!$D$11)),Assumptions!$F$11-SQRT((1-'Random Draws'!H14)*(Assumptions!$F$11-Assumptions!$D$11)*(Assumptions!$F$11-Assumptions!$E$11))) -> 0.16647024 | K14: =MAX(G14,I14+Assumptions!$D$21) -> 0.085893586 | L14: =(F14-Assumptions!$D$15)*(1-H14)+Assumptions!$D$15-J14 -> 0.15807702 | M14: =Assumptions!$D$14*(1+E14)^1*L14-Assumptions!$D$14*(1+E14)^0*E14*Assumptions!$D$16 -> 24.346105 | N14: =Assumptions!$D$14*(1+E14)^2*L14-Assumptions!$D$14*(1+E14)^1*E14*Assumptions!$D$16 -> 26.214146 | O14: =Assumptions!$D$14*(1+E14)^3*L14-Assumptions!$D$14*(1+E14)^2*E14*Assumptions!$D$16 -> 28.225518 | P14: =Assumptions!$D$14*(1+E14)^4*L14-Assumptions!$D$14*(1+E14)^3*E14*Assumptions!$D$16 -> 30.391219 | Q14: =Assumptions!$D$14*(1+E14)^5*L14-Assumptions!$D$14*(1+E14)^4*E14*Assumptions!$D$16 -> 32.723092 | R14: =M14/(1+K14)+N14/(1+K14)^2+O14/(1+K14)^3+P14/(1+K14)^4+Q14/(1+K14)^5 -> 110.22531 | S14: =Q14*(1+I14)/(K14-I14) -> 482.78709 | T14: =R14+S14/(1+K14)^5 -> 429.98175 | U14: =(T14-Assumptions!$D$17)/Assumptions!$D$18 -> 9.7992702
B15: 10 | C15: =NORMSDIST('Random Draws'!C15) -> 0.823045 | D15: =NORMSDIST(Assumptions!$D$22*'Random Draws'!C15+SQRT(1-Assumptions!$D$22^2)*'Random Draws'!D15) -> 0.74518449 | E15: =IF(C15<(Assumptions!$E$6-Assumptions!$D$6)/(Assumptions!$F$6-Assumptions!$D$6),Assumptions!$D$6+SQRT(C15*(Assumptions!$F$6-Assumptions!$D$6)*(Assumptions!$E$6-Assumptions!$D$6)),Assumptions!$F$6-SQRT((1-C15)*(Assumptions!$F$6-Assumptions!$D$6)*(Assumptions!$F$6-Assumptions!$E$6))) -> 0.11025483 | F15: =IF(D15<(Assumptions!$E$7-Assumptions!$D$7)/(Assumptions!$F$7-Assumptions!$D$7),Assumptions!$D$7+SQRT(D15*(Assumptions!$F$7-Assumptions!$D$7)*(Assumptions!$E$7-Assumptions!$D$7)),Assumptions!$F$7-SQRT((1-D15)*(Assumptions!$F$7-Assumptions!$D$7)*(Assumptions!$F$7-Assumptions!$E$7))) -> 0.42807412 | G15: =MIN(Assumptions!$D$24,MAX(Assumptions!$D$23,Assumptions!$D$8+Assumptions!$E$8*'Random Draws'!E15)) -> 0.072684625 | H15: =IF('Random Draws'!F15<(Assumptions!$E$9-Assumptions!$D$9)/(Assumptions!$F$9-Assumptions!$D$9),Assumptions!$D$9+SQRT('Random Draws'!F15*(Assumptions!$F$9-Assumptions!$D$9)*(Assumptions!$E$9-Assumptions!$D$9)),Assumptions!$F$9-SQRT((1-'Random Draws'!F15)*(Assumptions!$F$9-Assumptions!$D$9)*(Assumptions!$F$9-Assumptions!$E$9))) -> 0.27454476 | I15: =IF('Random Draws'!G15<(Assumptions!$E$10-Assumptions!$D$10)/(Assumptions!$F$10-Assumptions!$D$10),Assumptions!$D$10+SQRT('Random Draws'!G15*(Assumptions!$F$10-Assumptions!$D$10)*(Assumptions!$E$10-Assumptions!$D$10)),Assumptions!$F$10-SQRT((1-'Random Draws'!G15)*(Assumptions!$F$10-Assumptions!$D$10)*(Assumptions!$F$10-Assumptions!$E$10))) -> 0.023108314 | J15: =IF('Random Draws'!H15<(Assumptions!$E$11-Assumptions!$D$11)/(Assumptions!$F$11-Assumptions!$D$11),Assumptions!$D$11+SQRT('Random Draws'!H15*(Assumptions!$F$11-Assumptions!$D$11)*(Assumptions!$E$11-Assumptions!$D$11)),Assumptions!$F$11-SQRT((1-'Random Draws'!H15)*(Assumptions!$F$11-Assumptions!$D$11)*(Assumptions!$F$11-Assumptions!$E$11))) -> 0.18427983 | K15: =MAX(G15,I15+Assumptions!$D$21) -> 0.072684625 | L15: =(F15-Assumptions!$D$15)*(1-H15)+Assumptions!$D$15-J15 -> 0.16195959 | M15: =Assumptions!$D$14*(1+E15)^1*L15-Assumptions!$D$14*(1+E15)^0*E15*Assumptions!$D$16 -> 25.593773 | N15: =Assumptions!$D$14*(1+E15)^2*L15-Assumptions!$D$14*(1+E15)^1*E15*Assumptions!$D$16 -> 28.41561 | O15: =Assumptions!$D$14*(1+E15)^3*L15-Assumptions!$D$14*(1+E15)^2*E15*Assumptions!$D$16 -> 31.548568 | P15: =Assumptions!$D$14*(1+E15)^4*L15-Assumptions!$D$14*(1+E15)^3*E15*Assumptions!$D$16 -> 35.02695 | Q15: =Assumptions!$D$14*(1+E15)^5*L15-Assumptions!$D$14*(1+E15)^4*E15*Assumptions!$D$16 -> 38.888841 | R15: =M15/(1+K15)+N15/(1+K15)^2+O15/(1+K15)^3+P15/(1+K15)^4+Q15/(1+K15)^5 -> 127.95228 | S15: =Q15*(1+I15)/(K15-I15) -> 802.55056 | T15: =R15+S15/(1+K15)^5 -> 693.03512 | U15: =(T15-Assumptions!$D$17)/Assumptions!$D$18 -> 20.321405
B16: 11 | C16: =NORMSDIST('Random Draws'!C16) -> 0.021973619 | D16: =NORMSDIST(Assumptions!$D$22*'Random Draws'!C16+SQRT(1-Assumptions!$D$22^2)*'Random Draws'!D16) -> 0.11617985 | E16: =IF(C16<(Assumptions!$E$6-Assumptions!$D$6)/(Assumptions!$F$6-Assumptions!$D$6),Assumptions!$D$6+SQRT(C16*(Assumptions!$F$6-Assumptions!$D$6)*(Assumptions!$E$6-Assumptions!$D$6)),Assumptions!$F$6-SQRT((1-C16)*(Assumptions!$F$6-Assumptions!$D$6)*(Assumptions!$F$6-Assumptions!$E$6))) -> 0.050481798 | F16: =IF(D16<(Assumptions!$E$7-Assumptions!$D$7)/(Assumptions!$F$7-Assumptions!$D$7),Assumptions!$D$7+SQRT(D16*(Assumptions!$F$7-Assumptions!$D$7)*(Assumptions!$E$7-Assumptions!$D$7)),Assumptions!$F$7-SQRT((1-D16)*(Assumptions!$F$7-Assumptions!$D$7)*(Assumptions!$F$7-Assumptions!$E$7))) -> 0.38640226 | G16: =MIN(Assumptions!$D$24,MAX(Assumptions!$D$23,Assumptions!$D$8+Assumptions!$E$8*'Random Draws'!E16)) -> 0.078816548 | H16: =IF('Random Draws'!F16<(Assumptions!$E$9-Assumptions!$D$9)/(Assumptions!$F$9-Assumptions!$D$9),Assumptions!$D$9+SQRT('Random Draws'!F16*(Assumptions!$F$9-Assumptions!$D$9)*(Assumptions!$E$9-Assumptions!$D$9)),Assumptions!$F$9-SQRT((1-'Random Draws'!F16)*(Assumptions!$F$9-Assumptions!$D$9)*(Assumptions!$F$9-Assumptions!$E$9))) -> 0.27774353 | I16: =IF('Random Draws'!G16<(Assumptions!$E$10-Assumptions!$D$10)/(Assumptions!$F$10-Assumptions!$D$10),Assumptions!$D$10+SQRT('Random Draws'!G16*(Assumptions!$F$10-Assumptions!$D$10)*(Assumptions!$E$10-Assumptions!$D$10)),Assumptions!$F$10-SQRT((1-'Random Draws'!G16)*(Assumptions!$F$10-Assumptions!$D$10)*(Assumptions!$F$10-Assumptions!$E$10))) -> 0.014062312 | J16: =IF('Random Draws'!H16<(Assumptions!$E$11-Assumptions!$D$11)/(Assumptions!$F$11-Assumptions!$D$11),Assumptions!$D$11+SQRT('Random Draws'!H16*(Assumptions!$F$11-Assumptions!$D$11)*(Assumptions!$E$11-Assumptions!$D$11)),Assumptions!$F$11-SQRT((1-'Random Draws'!H16)*(Assumptions!$F$11-Assumptions!$D$11)*(Assumptions!$F$11-Assumptions!$E$11))) -> 0.1415003 | K16: =MAX(G16,I16+Assumptions!$D$21) -> 0.078816548 | L16: =(F16-Assumptions!$D$15)*(1-H16)+Assumptions!$D$15-J16 -> 0.17368789 | M16: =Assumptions!$D$14*(1+E16)^1*L16-Assumptions!$D$14*(1+E16)^0*E16*Assumptions!$D$16 -> 26.236519 | N16: =Assumptions!$D$14*(1+E16)^2*L16-Assumptions!$D$14*(1+E16)^1*E16*Assumptions!$D$16 -> 27.560986 | O16: =Assumptions!$D$14*(1+E16)^3*L16-Assumptions!$D$14*(1+E16)^2*E16*Assumptions!$D$16 -> 28.952314 | P16: =Assumptions!$D$14*(1+E16)^4*L16-Assumptions!$D$14*(1+E16)^3*E16*Assumptions!$D$16 -> 30.413879 | Q16: =Assumptions!$D$14*(1+E16)^5*L16-Assumptions!$D$14*(1+E16)^4*E16*Assumptions!$D$16 -> 31.949226 | R16: =M16/(1+K16)+N16/(1+K16)^2+O16/(1+K16)^3+P16/(1+K16)^4+Q16/(1+K16)^5 -> 115.37669 | S16: =Q16*(1+I16)/(K16-I16) -> 500.3303 | T16: =R16+S16/(1+K16)^5 -> 457.76491 | U16: =(T16-Assumptions!$D$17)/Assumptions!$D$18 -> 10.910596
B17: 12 | C17: =NORMSDIST('Random Draws'!C17) -> 0.31447627 | D17: =NORMSDIST(Assumptions!$D$22*'Random Draws'!C17+SQRT(1-Assumptions!$D$22^2)*'Random Draws'!D17) -> 0.95974599 | E17: =IF(C17<(Assumptions!$E$6-Assumptions!$D$6)/(Assumptions!$F$6-Assumptions!$D$6),Assumptions!$D$6+SQRT(C17*(Assumptions!$F$6-Assumptions!$D$6)*(Assumptions!$E$6-Assumptions!$D$6)),Assumptions!$F$6-SQRT((1-C17)*(Assumptions!$F$6-Assumptions!$D$6)*(Assumptions!$F$6-Assumptions!$E$6))) -> 0.079653264 | F17: =IF(D17<(Assumptions!$E$7-Assumptions!$D$7)/(Assumptions!$F$7-Assumptions!$D$7),Assumptions!$D$7+SQRT(D17*(Assumptions!$F$7-Assumptions!$D$7)*(Assumptions!$E$7-Assumptions!$D$7)),Assumptions!$F$7-SQRT((1-D17)*(Assumptions!$F$7-Assumptions!$D$7)*(Assumptions!$F$7-Assumptions!$E$7))) -> 0.44731079 | G17: =MIN(Assumptions!$D$24,MAX(Assumptions!$D$23,Assumptions!$D$8+Assumptions!$E$8*'Random Draws'!E17)) -> 0.076183311 | H17: =IF('Random Draws'!F17<(Assumptions!$E$9-Assumptions!$D$9)/(Assumptions!$F$9-Assumptions!$D$9),Assumptions!$D$9+SQRT('Random Draws'!F17*(Assumptions!$F$9-Assumptions!$D$9)*(Assumptions!$E$9-Assumptions!$D$9)),Assumptions!$F$9-SQRT((1-'Random Draws'!F17)*(Assumptions!$F$9-Assumptions!$D$9)*(Assumptions!$F$9-Assumptions!$E$9))) -> 0.25911655 | I17: =IF('Random Draws'!G17<(Assumptions!$E$10-Assumptions!$D$10)/(Assumptions!$F$10-Assumptions!$D$10),Assumptions!$D$10+SQRT('Random Draws'!G17*(Assumptions!$F$10-Assumptions!$D$10)*(Assumptions!$E$10-Assumptions!$D$10)),Assumptions!$F$10-SQRT((1-'Random Draws'!G17)*(Assumptions!$F$10-Assumptions!$D$10)*(Assumptions!$F$10-Assumptions!$E$10))) -> 0.014878821 | J17: =IF('Random Draws'!H17<(Assumptions!$E$11-Assumptions!$D$11)/(Assumptions!$F$11-Assumptions!$D$11),Assumptions!$D$11+SQRT('Random Draws'!H17*(Assumptions!$F$11-Assumptions!$D$11)*(Assumptions!$E$11-Assumptions!$D$11)),Assumptions!$F$11-SQRT((1-'Random Draws'!H17)*(Assumptions!$F$11-Assumptions!$D$11)*(Assumptions!$F$11-Assumptions!$E$11))) -> 0.15186201 | K17: =MAX(G17,I17+Assumptions!$D$21) -> 0.076183311 | L17: =(F17-Assumptions!$D$15)*(1-H17)+Assumptions!$D$15-J17 -> 0.2132283 | M17: =Assumptions!$D$14*(1+E17)^1*L17-Assumptions!$D$14*(1+E17)^0*E17*Assumptions!$D$16 -> 33.03434 | N17: =Assumptions!$D$14*(1+E17)^2*L17-Assumptions!$D$14*(1+E17)^1*E17*Assumptions!$D$16 -> 35.665633 | O17: =Assumptions!$D$14*(1+E17)^3*L17-Assumptions!$D$14*(1+E17)^2*E17*Assumptions!$D$16 -> 38.506517 | P17: =Assumptions!$D$14*(1+E17)^4*L17-Assumptions!$D$14*(1+E17)^3*E17*Assumptions!$D$16 -> 41.573687 | Q17: =Assumptions!$D$14*(1+E17)^5*L17-Assumptions!$D$14*(1+E17)^4*E17*Assumptions!$D$16 -> 44.885167 | R17: =M17/(1+K17)+N17/(1+K17)^2+O17/(1+K17)^3+P17/(1+K17)^4+Q17/(1+K17)^5 -> 154.47208 | S17: =Q17*(1+I17)/(K17-I17) -> 743.06149 | T17: =R17+S17/(1+K17)^5 -> 669.21868 | U17: =(T17-Assumptions!$D$17)/Assumptions!$D$18 -> 19.368747
... B2005: 2000 | C2005: =NORMSDIST('Random Draws'!C2005) -> 0.1721119 | D2005: =NORMSDIST(Assumptions!$D$22*'Random Draws'!C2005+SQRT(1-Assumptions!$D$22^2)*'Random Draws'!D2005) -> 0.95227585 | E2005: =IF(C2005<(Assumptions!$E$6-Assumptions!$D$6)/(Assumptions!$F$6-Assumptions!$D$6),Assumptions!$D$6+SQRT(C2005*(Assumptions!$F$6-Assumptions!$D$6)*(Assumptions!$E$6-Assumptions!$D$6)),Assumptions!$F$6-SQRT((1-C2005)*(Assumptions!$F$6-Assumptions!$D$6)*(Assumptions!$F$6-Assumptions!$E$6))) -> 0.069335294 | F2005: =IF(D2005<(Assumptions!$E$7-Assumptions!$D$7)/(Assumptions!$F$7-Assumptions!$D$7),Assumptions!$D$7+SQRT(D2005*(Assumptions!$F$7-Assumptions!$D$7)*(Assumptions!$E$7-Assumptions!$D$7)),Assumptions!$F$7-SQRT((1-D2005)*(Assumptions!$F$7-Assumptions!$D$7)*(Assumptions!$F$7-Assumptions!$E$7))) -> 0.44618347 | G2005: =MIN(Assumptions!$D$24,MAX(Assumptions!$D$23,Assumptions!$D$8+Assumptions!$E$8*'Random Draws'!E2005)) -> 0.069567616 | H2005: =IF('Random Draws'!F2005<(Assumptions!$E$9-Assumptions!$D$9)/(Assumptions!$F$9-Assumptions!$D$9),Assumptions!$D$9+SQRT('Random Draws'!F2005*(Assumptions!$F$9-Assumptions!$D$9)*(Assumptions!$E$9-Assumptions!$D$9)),Assumptions!$F$9-SQRT((1-'Random Draws'!F2005)*(Assumptions!$F$9-Assumptions!$D$9)*(Assumptions!$F$9-Assumptions!$E$9))) -> 0.24967444 | I2005: =IF('Random Draws'!G2005<(Assumptions!$E$10-Assumptions!$D$10)/(Assumptions!$F$10-Assumptions!$D$10),Assumptions!$D$10+SQRT('Random Draws'!G2005*(Assumptions!$F$10-Assumptions!$D$10)*(Assumptions!$E$10-Assumptions!$D$10)),Assumptions!$F$10-SQRT((1-'Random Draws'!G2005)*(Assumptions!$F$10-Assumptions!$D$10)*(Assumptions!$F$10-Assumptions!$E$10))) -> 0.020186164 | J2005: =IF('Random Draws'!H2005<(Assumptions!$E$11-Assumptions!$D$11)/(Assumptions!$F$11-Assumptions!$D$11),Assumptions!$D$11+SQRT('Random Draws'!H2005*(Assumptions!$F$11-Assumptions!$D$11)*(Assumptions!$E$11-Assumptions!$D$11)),Assumptions!$F$11-SQRT((1-'Random Draws'!H2005)*(Assumptions!$F$11-Assumptions!$D$11)*(Assumptions!$F$11-Assumptions!$E$11))) -> 0.14333379 | K2005: =MAX(G2005,I2005+Assumptions!$D$21) -> 0.069567616 | L2005: =(F2005-Assumptions!$D$15)*(1-H2005)+Assumptions!$D$15-J2005 -> 0.22390675 | M2005: =Assumptions!$D$14*(1+E2005)^1*L2005-Assumptions!$D$14*(1+E2005)^0*E2005*Assumptions!$D$16 -> 34.415943 | N2005: =Assumptions!$D$14*(1+E2005)^2*L2005-Assumptions!$D$14*(1+E2005)^1*E2005*Assumptions!$D$16 -> 36.802182 | O2005: =Assumptions!$D$14*(1+E2005)^3*L2005-Assumptions!$D$14*(1+E2005)^2*E2005*Assumptions!$D$16 -> 39.353872 | P2005: =Assumptions!$D$14*(1+E2005)^4*L2005-Assumptions!$D$14*(1+E2005)^3*E2005*Assumptions!$D$16 -> 42.082485 | Q2005: =Assumptions!$D$14*(1+E2005)^5*L2005-Assumptions!$D$14*(1+E2005)^4*E2005*Assumptions!$D$16 -> 45.000286 | R2005: =M2005/(1+K2005)+N2005/(1+K2005)^2+O2005/(1+K2005)^3+P2005/(1+K2005)^4+Q2005/(1+K2005)^5 -> 160.8173 | S2005: =Q2005*(1+I2005)/(K2005-I2005) -> 929.67436 | T2005: =R2005+S2005/(1+K2005)^5 -> 825.00316 | U2005: =(T2005-Assumptions!$D$17)/Assumptions!$D$18 -> 25.600126

Sheet Results
B2: Results
B3: Statistics of the 2,000 live iterations, value per share in €
B5: Statistic | C5: Live | E5: From € | F5: To € | G5: Iterations
B6: Mean | C6: =AVERAGE(Simulation!$U$6:$U$2005) -> 13.40285 | E6: 0 | F6: 2 | G6: =COUNTIFS(Simulation!$U$6:$U$2005,">"&E6,Simulation!$U$6:$U$2005,"<="&F6) -> 7
B7: Median (P50) | C7: =MEDIAN(Simulation!$U$6:$U$2005) -> 12.553903 | E7: 2 | F7: 4 | G7: =COUNTIFS(Simulation!$U$6:$U$2005,">"&E7,Simulation!$U$6:$U$2005,"<="&F7) -> 34
B8: Standard deviation | C8: =STDEV(Simulation!$U$6:$U$2005) -> 5.9594537 | E8: 4 | F8: 6 | G8: =COUNTIFS(Simulation!$U$6:$U$2005,">"&E8,Simulation!$U$6:$U$2005,"<="&F8) -> 101
B9: P5 | C9: =PERCENTILE(Simulation!$U$6:$U$2005,0.05) -> 5.4605247 | E9: 6 | F9: 8 | G9: =COUNTIFS(Simulation!$U$6:$U$2005,">"&E9,Simulation!$U$6:$U$2005,"<="&F9) -> 185
B10: P10 | C10: =PERCENTILE(Simulation!$U$6:$U$2005,0.1) -> 6.8168369 | E10: 8 | F10: 10 | G10: =COUNTIFS(Simulation!$U$6:$U$2005,">"&E10,Simulation!$U$6:$U$2005,"<="&F10) -> 287
B11: P25 | C11: =PERCENTILE(Simulation!$U$6:$U$2005,0.25) -> 9.3002311 | E11: 10 | F11: 12 | G11: =COUNTIFS(Simulation!$U$6:$U$2005,">"&E11,Simulation!$U$6:$U$2005,"<="&F11) -> 308
B12: P75 | C12: =PERCENTILE(Simulation!$U$6:$U$2005,0.75) -> 16.765063 | E12: 12 | F12: 14 | G12: =COUNTIFS(Simulation!$U$6:$U$2005,">"&E12,Simulation!$U$6:$U$2005,"<="&F12) -> 287
B13: P95 | C13: =PERCENTILE(Simulation!$U$6:$U$2005,0.95) -> 24.176302 | E13: 14 | F13: 16 | G13: =COUNTIFS(Simulation!$U$6:$U$2005,">"&E13,Simulation!$U$6:$U$2005,"<="&F13) -> 229
B14: Iterations | C14: =COUNT(Simulation!$U$6:$U$2005) -> 2000 | E14: 16 | F14: 18 | G14: =COUNTIFS(Simulation!$U$6:$U$2005,">"&E14,Simulation!$U$6:$U$2005,"<="&F14) -> 177
B15: P(value > market price) | C15: =COUNTIF(Simulation!$U$6:$U$2005,">"&Assumptions!$D$19)/C14 -> 0.58 | E15: 18 | F15: 20 | G15: =COUNTIFS(Simulation!$U$6:$U$2005,">"&E15,Simulation!$U$6:$U$2005,"<="&F15) -> 140
B16: P(value > base case) | C16: =COUNTIF(Simulation!$U$6:$U$2005,">"&'DCF Base Case'!C36)/C14 -> 0.329 | E16: 20 | F16: 22 | G16: =COUNTIFS(Simulation!$U$6:$U$2005,">"&E16,Simulation!$U$6:$U$2005,"<="&F16) -> 85
B17: P(value < €8.00) | C17: =COUNTIF(Simulation!$U$6:$U$2005,"<8")/C14 -> 0.1635 | E17: 22 | F17: 24 | G17: =COUNTIFS(Simulation!$U$6:$U$2005,">"&E17,Simulation!$U$6:$U$2005,"<="&F17) -> 57
E18: 24 | F18: 26 | G18: =COUNTIFS(Simulation!$U$6:$U$2005,">"&E18,Simulation!$U$6:$U$2005,"<="&F18) -> 30
E19: 26 | F19: 28 | G19: =COUNTIFS(Simulation!$U$6:$U$2005,">"&E19,Simulation!$U$6:$U$2005,"<="&F19) -> 24
E20: 28 | F20: 30 | G20: =COUNTIFS(Simulation!$U$6:$U$2005,">"&E20,Simulation!$U$6:$U$2005,"<="&F20) -> 12
E21: 30 | F21: 32 | G21: =COUNTIFS(Simulation!$U$6:$U$2005,">"&E21,Simulation!$U$6:$U$2005,"<="&F21) -> 14
E22: 32 | F22: 34 | G22: =COUNTIFS(Simulation!$U$6:$U$2005,">"&E22,Simulation!$U$6:$U$2005,"<="&F22) -> 12
E23: 34 | F23: 36 | G23: =COUNTIFS(Simulation!$U$6:$U$2005,">"&E23,Simulation!$U$6:$U$2005,"<="&F23) -> 3
E24: Outside €0 to €36 | G24: =C14-SUM(G6:G23) -> 8

Sheet Sensitivity
B2: Sensitivity
B3: Which uncertainty moves value most
B5: Driver | C5: Live correlation | D5: Rank correlation (50,000) | E5: Share of variance (50,000) | F5: Reading
B6: WACC | C6: =CORREL(Simulation!$G$6:$G$2005,Simulation!$U$6:$U$2005) -> -0.67931445 | D6: -0.63077714 | E6: 0.38372835 | F6: The largest single driver: it discounts every cash flow and the terminal value
B7: CapEx (% of revenue) | C7: =CORREL(Simulation!$J$6:$J$2005,Simulation!$U$6:$U$2005) -> -0.45329599 | D7: -0.47382949 | E7: 0.21652905 | F7: Every point of revenue spent on CapEx is lost free cash flow
B8: EBITDA margin | C8: =CORREL(Simulation!$F$6:$F$2005,Simulation!$U$6:$U$2005) -> 0.44170404 | D8: 0.4378483 | E8: 0.18489252 | F8: Moves with growth through the copula
B9: Revenue growth | C9: =CORREL(Simulation!$E$6:$E$2005,Simulation!$U$6:$U$2005) -> 0.40015529 | D9: 0.41723055 | E9: 0.16788976 | F9: Compounds over five years and into the terminal value
B10: Terminal growth | C10: =CORREL(Simulation!$I$6:$I$2005,Simulation!$U$6:$U$2005) -> 0.16024055 | D10: 0.15855076 | E10: 0.024244243 | F10: Small range, but it sits inside the terminal value
B11: Tax rate | C11: =CORREL(Simulation!$H$6:$H$2005,Simulation!$U$6:$U$2005) -> -0.14872139 | D11: -0.15347259 | E11: 0.022716094 | F11: Narrow most of the time; its tail is the windfall risk
B13: Live: Pearson correlation on this workbook's iterations. Rank (Spearman) correlations and shares of variance come from the Python 50,000-iteration run; the share is each squared rank correlation over the total.

Sheet Windfall
B2: Windfall tax as an event
B3: Same random numbers as the Simulation sheet; only the tax changes: an ordinary rate, plus a surcharge that either happens or not
B5: Iter | C5: Ordinary tax | D5: Surcharge? | E5: Tax | F5: FCF per € rev. | G5: Value per share | H5: Value if surcharge | I5: No surcharge | K5: Summary, value per share | L5: Event model | M5: If surcharge | N5: No surcharge
B6: 1 | C6: =IF('Random Draws'!F6<(Assumptions!$D$28-Assumptions!$D$27)/(Assumptions!$D$29-Assumptions!$D$27),Assumptions!$D$27+SQRT('Random Draws'!F6*(Assumptions!$D$29-Assumptions!$D$27)*(Assumptions!$D$28-Assumptions!$D$27)),Assumptions!$D$29-SQRT((1-'Random Draws'!F6)*(Assumptions!$D$29-Assumptions!$D$27)*(Assumptions!$D$29-Assumptions!$D$28))) -> 0.2743664 | D6: =IF('Random Draws'!I6<Assumptions!$D$30,1,0) -> 0 | E6: =C6+Assumptions!$D$31*D6 -> 0.2743664 | F6: =(Simulation!F6-Assumptions!$D$15)*(1-E6)+Assumptions!$D$15-Simulation!J6 -> 0.16308056 | G6: =((Assumptions!$D$14*(1+Simulation!E6)^1*F6-Assumptions!$D$14*(1+Simulation!E6)^0*Simulation!E6*Assumptions!$D$16)/(1+Simulation!K6)^1+(Assumptions!$D$14*(1+Simulation!E6)^2*F6-Assumptions!$D$14*(1+Simulation!E6)^1*Simulation!E6*Assumptions!$D$16)/(1+Simulation!K6)^2+(Assumptions!$D$14*(1+Simulation!E6)^3*F6-Assumptions!$D$14*(1+Simulation!E6)^2*Simulation!E6*Assumptions!$D$16)/(1+Simulation!K6)^3+(Assumptions!$D$14*(1+Simulation!E6)^4*F6-Assumptions!$D$14*(1+Simulation!E6)^3*Simulation!E6*Assumptions!$D$16)/(1+Simulation!K6)^4+(Assumptions!$D$14*(1+Simulation!E6)^5*F6-Assumptions!$D$14*(1+Simulation!E6)^4*Simulation!E6*Assumptions!$D$16)/(1+Simulation!K6)^5+(Assumptions!$D$14*(1+Simulation!E6)^5*F6-Assumptions!$D$14*(1+Simulation!E6)^4*Simulation!E6*Assumptions!$D$16)*(1+Simulation!I6)/(Simulation!K6-Simulation!I6)/(1+Simulation!K6)^5-Assumptions!$D$17)/Assumptions!$D$18 -> 16.82762 | H6: =IF(D6=1,G6,"") | I6: =IF(D6=0,G6,"") -> 16.82762 | K6: Iterations | L6: =COUNT($G$6:$G$2005) -> 2000 | M6: =COUNT($H$6:$H$2005) -> 509 | N6: =COUNT($I$6:$I$2005) -> 1491
B7: 2 | C7: =IF('Random Draws'!F7<(Assumptions!$D$28-Assumptions!$D$27)/(Assumptions!$D$29-Assumptions!$D$27),Assumptions!$D$27+SQRT('Random Draws'!F7*(Assumptions!$D$29-Assumptions!$D$27)*(Assumptions!$D$28-Assumptions!$D$27)),Assumptions!$D$29-SQRT((1-'Random Draws'!F7)*(Assumptions!$D$29-Assumptions!$D$27)*(Assumptions!$D$29-Assumptions!$D$28))) -> 0.27021836 | D7: =IF('Random Draws'!I7<Assumptions!$D$30,1,0) -> 0 | E7: =C7+Assumptions!$D$31*D7 -> 0.27021836 | F7: =(Simulation!F7-Assumptions!$D$15)*(1-E7)+Assumptions!$D$15-Simulation!J7 -> 0.15817604 | G7: =((Assumptions!$D$14*(1+Simulation!E7)^1*F7-Assumptions!$D$14*(1+Simulation!E7)^0*Simulation!E7*Assumptions!$D$16)/(1+Simulation!K7)^1+(Assumptions!$D$14*(1+Simulation!E7)^2*F7-Assumptions!$D$14*(1+Simulation!E7)^1*Simulation!E7*Assumptions!$D$16)/(1+Simulation!K7)^2+(Assumptions!$D$14*(1+Simulation!E7)^3*F7-Assumptions!$D$14*(1+Simulation!E7)^2*Simulation!E7*Assumptions!$D$16)/(1+Simulation!K7)^3+(Assumptions!$D$14*(1+Simulation!E7)^4*F7-Assumptions!$D$14*(1+Simulation!E7)^3*Simulation!E7*Assumptions!$D$16)/(1+Simulation!K7)^4+(Assumptions!$D$14*(1+Simulation!E7)^5*F7-Assumptions!$D$14*(1+Simulation!E7)^4*Simulation!E7*Assumptions!$D$16)/(1+Simulation!K7)^5+(Assumptions!$D$14*(1+Simulation!E7)^5*F7-Assumptions!$D$14*(1+Simulation!E7)^4*Simulation!E7*Assumptions!$D$16)*(1+Simulation!I7)/(Simulation!K7-Simulation!I7)/(1+Simulation!K7)^5-Assumptions!$D$17)/Assumptions!$D$18 -> 19.006797 | H7: =IF(D7=1,G7,"") | I7: =IF(D7=0,G7,"") -> 19.006797 | K7: Median | L7: =MEDIAN($G$6:$G$2005) -> 12.513107 | M7: =MEDIAN($H$6:$H$2005) -> 10.019161 | N7: =MEDIAN($I$6:$I$2005) -> 13.561292
B8: 3 | C8: =IF('Random Draws'!F8<(Assumptions!$D$28-Assumptions!$D$27)/(Assumptions!$D$29-Assumptions!$D$27),Assumptions!$D$27+SQRT('Random Draws'!F8*(Assumptions!$D$29-Assumptions!$D$27)*(Assumptions!$D$28-Assumptions!$D$27)),Assumptions!$D$29-SQRT((1-'Random Draws'!F8)*(Assumptions!$D$29-Assumptions!$D$27)*(Assumptions!$D$29-Assumptions!$D$28))) -> 0.25930328 | D8: =IF('Random Draws'!I8<Assumptions!$D$30,1,0) -> 0 | E8: =C8+Assumptions!$D$31*D8 -> 0.25930328 | F8: =(Simulation!F8-Assumptions!$D$15)*(1-E8)+Assumptions!$D$15-Simulation!J8 -> 0.1515202 | G8: =((Assumptions!$D$14*(1+Simulation!E8)^1*F8-Assumptions!$D$14*(1+Simulation!E8)^0*Simulation!E8*Assumptions!$D$16)/(1+Simulation!K8)^1+(Assumptions!$D$14*(1+Simulation!E8)^2*F8-Assumptions!$D$14*(1+Simulation!E8)^1*Simulation!E8*Assumptions!$D$16)/(1+Simulation!K8)^2+(Assumptions!$D$14*(1+Simulation!E8)^3*F8-Assumptions!$D$14*(1+Simulation!E8)^2*Simulation!E8*Assumptions!$D$16)/(1+Simulation!K8)^3+(Assumptions!$D$14*(1+Simulation!E8)^4*F8-Assumptions!$D$14*(1+Simulation!E8)^3*Simulation!E8*Assumptions!$D$16)/(1+Simulation!K8)^4+(Assumptions!$D$14*(1+Simulation!E8)^5*F8-Assumptions!$D$14*(1+Simulation!E8)^4*Simulation!E8*Assumptions!$D$16)/(1+Simulation!K8)^5+(Assumptions!$D$14*(1+Simulation!E8)^5*F8-Assumptions!$D$14*(1+Simulation!E8)^4*Simulation!E8*Assumptions!$D$16)*(1+Simulation!I8)/(Simulation!K8-Simulation!I8)/(1+Simulation!K8)^5-Assumptions!$D$17)/Assumptions!$D$18 -> 10.323944 | H8: =IF(D8=1,G8,"") | I8: =IF(D8=0,G8,"") -> 10.323944 | K8: P5 | L8: =PERCENTILE($G$6:$G$2005,0.05) -> 5.2127091 | M8: =PERCENTILE($H$6:$H$2005,0.05) -> 3.4823152 | N8: =PERCENTILE($I$6:$I$2005,0.05) -> 6.1831509
B9: 4 | C9: =IF('Random Draws'!F9<(Assumptions!$D$28-Assumptions!$D$27)/(Assumptions!$D$29-Assumptions!$D$27),Assumptions!$D$27+SQRT('Random Draws'!F9*(Assumptions!$D$29-Assumptions!$D$27)*(Assumptions!$D$28-Assumptions!$D$27)),Assumptions!$D$29-SQRT((1-'Random Draws'!F9)*(Assumptions!$D$29-Assumptions!$D$27)*(Assumptions!$D$29-Assumptions!$D$28))) -> 0.26497705 | D9: =IF('Random Draws'!I9<Assumptions!$D$30,1,0) -> 0 | E9: =C9+Assumptions!$D$31*D9 -> 0.26497705 | F9: =(Simulation!F9-Assumptions!$D$15)*(1-E9)+Assumptions!$D$15-Simulation!J9 -> 0.20164557 | G9: =((Assumptions!$D$14*(1+Simulation!E9)^1*F9-Assumptions!$D$14*(1+Simulation!E9)^0*Simulation!E9*Assumptions!$D$16)/(1+Simulation!K9)^1+(Assumptions!$D$14*(1+Simulation!E9)^2*F9-Assumptions!$D$14*(1+Simulation!E9)^1*Simulation!E9*Assumptions!$D$16)/(1+Simulation!K9)^2+(Assumptions!$D$14*(1+Simulation!E9)^3*F9-Assumptions!$D$14*(1+Simulation!E9)^2*Simulation!E9*Assumptions!$D$16)/(1+Simulation!K9)^3+(Assumptions!$D$14*(1+Simulation!E9)^4*F9-Assumptions!$D$14*(1+Simulation!E9)^3*Simulation!E9*Assumptions!$D$16)/(1+Simulation!K9)^4+(Assumptions!$D$14*(1+Simulation!E9)^5*F9-Assumptions!$D$14*(1+Simulation!E9)^4*Simulation!E9*Assumptions!$D$16)/(1+Simulation!K9)^5+(Assumptions!$D$14*(1+Simulation!E9)^5*F9-Assumptions!$D$14*(1+Simulation!E9)^4*Simulation!E9*Assumptions!$D$16)*(1+Simulation!I9)/(Simulation!K9-Simulation!I9)/(1+Simulation!K9)^5-Assumptions!$D$17)/Assumptions!$D$18 -> 12.765651 | H9: =IF(D9=1,G9,"") | I9: =IF(D9=0,G9,"") -> 12.765651 | K9: P(value > market price) | L9: =COUNTIF($G$6:$G$2005,">"&Assumptions!$D$19)/L6 -> 0.567 | M9: =COUNTIF($H$6:$H$2005,">"&Assumptions!$D$19)/M6 -> 0.37131631 | N9: =COUNTIF($I$6:$I$2005,">"&Assumptions!$D$19)/N6 -> 0.63380282
B10: 5 | C10: =IF('Random Draws'!F10<(Assumptions!$D$28-Assumptions!$D$27)/(Assumptions!$D$29-Assumptions!$D$27),Assumptions!$D$27+SQRT('Random Draws'!F10*(Assumptions!$D$29-Assumptions!$D$27)*(Assumptions!$D$28-Assumptions!$D$27)),Assumptions!$D$29-SQRT((1-'Random Draws'!F10)*(Assumptions!$D$29-Assumptions!$D$27)*(Assumptions!$D$29-Assumptions!$D$28))) -> 0.25063744 | D10: =IF('Random Draws'!I10<Assumptions!$D$30,1,0) -> 1 | E10: =C10+Assumptions!$D$31*D10 -> 0.34063744 | F10: =(Simulation!F10-Assumptions!$D$15)*(1-E10)+Assumptions!$D$15-Simulation!J10 -> 0.13796122 | G10: =((Assumptions!$D$14*(1+Simulation!E10)^1*F10-Assumptions!$D$14*(1+Simulation!E10)^0*Simulation!E10*Assumptions!$D$16)/(1+Simulation!K10)^1+(Assumptions!$D$14*(1+Simulation!E10)^2*F10-Assumptions!$D$14*(1+Simulation!E10)^1*Simulation!E10*Assumptions!$D$16)/(1+Simulation!K10)^2+(Assumptions!$D$14*(1+Simulation!E10)^3*F10-Assumptions!$D$14*(1+Simulation!E10)^2*Simulation!E10*Assumptions!$D$16)/(1+Simulation!K10)^3+(Assumptions!$D$14*(1+Simulation!E10)^4*F10-Assumptions!$D$14*(1+Simulation!E10)^3*Simulation!E10*Assumptions!$D$16)/(1+Simulation!K10)^4+(Assumptions!$D$14*(1+Simulation!E10)^5*F10-Assumptions!$D$14*(1+Simulation!E10)^4*Simulation!E10*Assumptions!$D$16)/(1+Simulation!K10)^5+(Assumptions!$D$14*(1+Simulation!E10)^5*F10-Assumptions!$D$14*(1+Simulation!E10)^4*Simulation!E10*Assumptions!$D$16)*(1+Simulation!I10)/(Simulation!K10-Simulation!I10)/(1+Simulation!K10)^5-Assumptions!$D$17)/Assumptions!$D$18 -> 6.5327709 | H10: =IF(D10=1,G10,"") -> 6.5327709 | I10: =IF(D10=0,G10,"") | K10: Average tax | L10: =AVERAGE($E$6:$E$2005) -> 0.28306714
B11: 6 | C11: =IF('Random Draws'!F11<(Assumptions!$D$28-Assumptions!$D$27)/(Assumptions!$D$29-Assumptions!$D$27),Assumptions!$D$27+SQRT('Random Draws'!F11*(Assumptions!$D$29-Assumptions!$D$27)*(Assumptions!$D$28-Assumptions!$D$27)),Assumptions!$D$29-SQRT((1-'Random Draws'!F11)*(Assumptions!$D$29-Assumptions!$D$27)*(Assumptions!$D$29-Assumptions!$D$28))) -> 0.27241864 | D11: =IF('Random Draws'!I11<Assumptions!$D$30,1,0) -> 0 | E11: =C11+Assumptions!$D$31*D11 -> 0.27241864 | F11: =(Simulation!F11-Assumptions!$D$15)*(1-E11)+Assumptions!$D$15-Simulation!J11 -> 0.1318317 | G11: =((Assumptions!$D$14*(1+Simulation!E11)^1*F11-Assumptions!$D$14*(1+Simulation!E11)^0*Simulation!E11*Assumptions!$D$16)/(1+Simulation!K11)^1+(Assumptions!$D$14*(1+Simulation!E11)^2*F11-Assumptions!$D$14*(1+Simulation!E11)^1*Simulation!E11*Assumptions!$D$16)/(1+Simulation!K11)^2+(Assumptions!$D$14*(1+Simulation!E11)^3*F11-Assumptions!$D$14*(1+Simulation!E11)^2*Simulation!E11*Assumptions!$D$16)/(1+Simulation!K11)^3+(Assumptions!$D$14*(1+Simulation!E11)^4*F11-Assumptions!$D$14*(1+Simulation!E11)^3*Simulation!E11*Assumptions!$D$16)/(1+Simulation!K11)^4+(Assumptions!$D$14*(1+Simulation!E11)^5*F11-Assumptions!$D$14*(1+Simulation!E11)^4*Simulation!E11*Assumptions!$D$16)/(1+Simulation!K11)^5+(Assumptions!$D$14*(1+Simulation!E11)^5*F11-Assumptions!$D$14*(1+Simulation!E11)^4*Simulation!E11*Assumptions!$D$16)*(1+Simulation!I11)/(Simulation!K11-Simulation!I11)/(1+Simulation!K11)^5-Assumptions!$D$17)/Assumptions!$D$18 -> 7.318313 | H11: =IF(D11=1,G11,"") | I11: =IF(D11=0,G11,"") -> 7.318313
B12: 7 | C12: =IF('Random Draws'!F12<(Assumptions!$D$28-Assumptions!$D$27)/(Assumptions!$D$29-Assumptions!$D$27),Assumptions!$D$27+SQRT('Random Draws'!F12*(Assumptions!$D$29-Assumptions!$D$27)*(Assumptions!$D$28-Assumptions!$D$27)),Assumptions!$D$29-SQRT((1-'Random Draws'!F12)*(Assumptions!$D$29-Assumptions!$D$27)*(Assumptions!$D$29-Assumptions!$D$28))) -> 0.24920767 | D12: =IF('Random Draws'!I12<Assumptions!$D$30,1,0) -> 0 | E12: =C12+Assumptions!$D$31*D12 -> 0.24920767 | F12: =(Simulation!F12-Assumptions!$D$15)*(1-E12)+Assumptions!$D$15-Simulation!J12 -> 0.18798186 | G12: =((Assumptions!$D$14*(1+Simulation!E12)^1*F12-Assumptions!$D$14*(1+Simulation!E12)^0*Simulation!E12*Assumptions!$D$16)/(1+Simulation!K12)^1+(Assumptions!$D$14*(1+Simulation!E12)^2*F12-Assumptions!$D$14*(1+Simulation!E12)^1*Simulation!E12*Assumptions!$D$16)/(1+Simulation!K12)^2+(Assumptions!$D$14*(1+Simulation!E12)^3*F12-Assumptions!$D$14*(1+Simulation!E12)^2*Simulation!E12*Assumptions!$D$16)/(1+Simulation!K12)^3+(Assumptions!$D$14*(1+Simulation!E12)^4*F12-Assumptions!$D$14*(1+Simulation!E12)^3*Simulation!E12*Assumptions!$D$16)/(1+Simulation!K12)^4+(Assumptions!$D$14*(1+Simulation!E12)^5*F12-Assumptions!$D$14*(1+Simulation!E12)^4*Simulation!E12*Assumptions!$D$16)/(1+Simulation!K12)^5+(Assumptions!$D$14*(1+Simulation!E12)^5*F12-Assumptions!$D$14*(1+Simulation!E12)^4*Simulation!E12*Assumptions!$D$16)*(1+Simulation!I12)/(Simulation!K12-Simulation!I12)/(1+Simulation!K12)^5-Assumptions!$D$17)/Assumptions!$D$18 -> 19.528478 | H12: =IF(D12=1,G12,"") | I12: =IF(D12=0,G12,"") -> 19.528478 | K12: Continuous model (Simulation sheet)
B13: 8 | C13: =IF('Random Draws'!F13<(Assumptions!$D$28-Assumptions!$D$27)/(Assumptions!$D$29-Assumptions!$D$27),Assumptions!$D$27+SQRT('Random Draws'!F13*(Assumptions!$D$29-Assumptions!$D$27)*(Assumptions!$D$28-Assumptions!$D$27)),Assumptions!$D$29-SQRT((1-'Random Draws'!F13)*(Assumptions!$D$29-Assumptions!$D$27)*(Assumptions!$D$29-Assumptions!$D$28))) -> 0.26575122 | D13: =IF('Random Draws'!I13<Assumptions!$D$30,1,0) -> 0 | E13: =C13+Assumptions!$D$31*D13 -> 0.26575122 | F13: =(Simulation!F13-Assumptions!$D$15)*(1-E13)+Assumptions!$D$15-Simulation!J13 -> 0.18606245 | G13: =((Assumptions!$D$14*(1+Simulation!E13)^1*F13-Assumptions!$D$14*(1+Simulation!E13)^0*Simulation!E13*Assumptions!$D$16)/(1+Simulation!K13)^1+(Assumptions!$D$14*(1+Simulation!E13)^2*F13-Assumptions!$D$14*(1+Simulation!E13)^1*Simulation!E13*Assumptions!$D$16)/(1+Simulation!K13)^2+(Assumptions!$D$14*(1+Simulation!E13)^3*F13-Assumptions!$D$14*(1+Simulation!E13)^2*Simulation!E13*Assumptions!$D$16)/(1+Simulation!K13)^3+(Assumptions!$D$14*(1+Simulation!E13)^4*F13-Assumptions!$D$14*(1+Simulation!E13)^3*Simulation!E13*Assumptions!$D$16)/(1+Simulation!K13)^4+(Assumptions!$D$14*(1+Simulation!E13)^5*F13-Assumptions!$D$14*(1+Simulation!E13)^4*Simulation!E13*Assumptions!$D$16)/(1+Simulation!K13)^5+(Assumptions!$D$14*(1+Simulation!E13)^5*F13-Assumptions!$D$14*(1+Simulation!E13)^4*Simulation!E13*Assumptions!$D$16)*(1+Simulation!I13)/(Simulation!K13-Simulation!I13)/(1+Simulation!K13)^5-Assumptions!$D$17)/Assumptions!$D$18 -> 20.270844 | H13: =IF(D13=1,G13,"") | I13: =IF(D13=0,G13,"") -> 20.270844 | K13: Median | L13: =Results!C7 -> 12.553903
B14: 9 | C14: =IF('Random Draws'!F14<(Assumptions!$D$28-Assumptions!$D$27)/(Assumptions!$D$29-Assumptions!$D$27),Assumptions!$D$27+SQRT('Random Draws'!F14*(Assumptions!$D$29-Assumptions!$D$27)*(Assumptions!$D$28-Assumptions!$D$27)),Assumptions!$D$29-SQRT((1-'Random Draws'!F14)*(Assumptions!$D$29-Assumptions!$D$27)*(Assumptions!$D$29-Assumptions!$D$28))) -> 0.26134853 | D14: =IF('Random Draws'!I14<Assumptions!$D$30,1,0) -> 0 | E14: =C14+Assumptions!$D$31*D14 -> 0.26134853 | F14: =(Simulation!F14-Assumptions!$D$15)*(1-E14)+Assumptions!$D$15-Simulation!J14 -> 0.16434046 | G14: =((Assumptions!$D$14*(1+Simulation!E14)^1*F14-Assumptions!$D$14*(1+Simulation!E14)^0*Simulation!E14*Assumptions!$D$16)/(1+Simulation!K14)^1+(Assumptions!$D$14*(1+Simulation!E14)^2*F14-Assumptions!$D$14*(1+Simulation!E14)^1*Simulation!E14*Assumptions!$D$16)/(1+Simulation!K14)^2+(Assumptions!$D$14*(1+Simulation!E14)^3*F14-Assumptions!$D$14*(1+Simulation!E14)^2*Simulation!E14*Assumptions!$D$16)/(1+Simulation!K14)^3+(Assumptions!$D$14*(1+Simulation!E14)^4*F14-Assumptions!$D$14*(1+Simulation!E14)^3*Simulation!E14*Assumptions!$D$16)/(1+Simulation!K14)^4+(Assumptions!$D$14*(1+Simulation!E14)^5*F14-Assumptions!$D$14*(1+Simulation!E14)^4*Simulation!E14*Assumptions!$D$16)/(1+Simulation!K14)^5+(Assumptions!$D$14*(1+Simulation!E14)^5*F14-Assumptions!$D$14*(1+Simulation!E14)^4*Simulation!E14*Assumptions!$D$16)*(1+Simulation!I14)/(Simulation!K14-Simulation!I14)/(1+Simulation!K14)^5-Assumptions!$D$17)/Assumptions!$D$18 -> 10.490095 | H14: =IF(D14=1,G14,"") | I14: =IF(D14=0,G14,"") -> 10.490095 | K14: Average tax | L14: =AVERAGE(Simulation!$H$6:$H$2005) -> 0.28374809
B15: 10 | C15: =IF('Random Draws'!F15<(Assumptions!$D$28-Assumptions!$D$27)/(Assumptions!$D$29-Assumptions!$D$27),Assumptions!$D$27+SQRT('Random Draws'!F15*(Assumptions!$D$29-Assumptions!$D$27)*(Assumptions!$D$28-Assumptions!$D$27)),Assumptions!$D$29-SQRT((1-'Random Draws'!F15)*(Assumptions!$D$29-Assumptions!$D$27)*(Assumptions!$D$29-Assumptions!$D$28))) -> 0.25843691 | D15: =IF('Random Draws'!I15<Assumptions!$D$30,1,0) -> 0 | E15: =C15+Assumptions!$D$31*D15 -> 0.25843691 | F15: =(Simulation!F15-Assumptions!$D$15)*(1-E15)+Assumptions!$D$15-Simulation!J15 -> 0.16676093 | G15: =((Assumptions!$D$14*(1+Simulation!E15)^1*F15-Assumptions!$D$14*(1+Simulation!E15)^0*Simulation!E15*Assumptions!$D$16)/(1+Simulation!K15)^1+(Assumptions!$D$14*(1+Simulation!E15)^2*F15-Assumptions!$D$14*(1+Simulation!E15)^1*Simulation!E15*Assumptions!$D$16)/(1+Simulation!K15)^2+(Assumptions!$D$14*(1+Simulation!E15)^3*F15-Assumptions!$D$14*(1+Simulation!E15)^2*Simulation!E15*Assumptions!$D$16)/(1+Simulation!K15)^3+(Assumptions!$D$14*(1+Simulation!E15)^4*F15-Assumptions!$D$14*(1+Simulation!E15)^3*Simulation!E15*Assumptions!$D$16)/(1+Simulation!K15)^4+(Assumptions!$D$14*(1+Simulation!E15)^5*F15-Assumptions!$D$14*(1+Simulation!E15)^4*Simulation!E15*Assumptions!$D$16)/(1+Simulation!K15)^5+(Assumptions!$D$14*(1+Simulation!E15)^5*F15-Assumptions!$D$14*(1+Simulation!E15)^4*Simulation!E15*Assumptions!$D$16)*(1+Simulation!I15)/(Simulation!K15-Simulation!I15)/(1+Simulation!K15)^5-Assumptions!$D$17)/Assumptions!$D$18 -> 21.158613 | H15: =IF(D15=1,G15,"") | I15: =IF(D15=0,G15,"") -> 21.158613
B16: 11 | C16: =IF('Random Draws'!F16<(Assumptions!$D$28-Assumptions!$D$27)/(Assumptions!$D$29-Assumptions!$D$27),Assumptions!$D$27+SQRT('Random Draws'!F16*(Assumptions!$D$29-Assumptions!$D$27)*(Assumptions!$D$28-Assumptions!$D$27)),Assumptions!$D$29-SQRT((1-'Random Draws'!F16)*(Assumptions!$D$29-Assumptions!$D$27)*(Assumptions!$D$29-Assumptions!$D$28))) -> 0.25944482 | D16: =IF('Random Draws'!I16<Assumptions!$D$30,1,0) -> 0 | E16: =C16+Assumptions!$D$31*D16 -> 0.25944482 | F16: =(Simulation!F16-Assumptions!$D$15)*(1-E16)+Assumptions!$D$15-Simulation!J16 -> 0.17837972 | G16: =((Assumptions!$D$14*(1+Simulation!E16)^1*F16-Assumptions!$D$14*(1+Simulation!E16)^0*Simulation!E16*Assumptions!$D$16)/(1+Simulation!K16)^1+(Assumptions!$D$14*(1+Simulation!E16)^2*F16-Assumptions!$D$14*(1+Simulation!E16)^1*Simulation!E16*Assumptions!$D$16)/(1+Simulation!K16)^2+(Assumptions!$D$14*(1+Simulation!E16)^3*F16-Assumptions!$D$14*(1+Simulation!E16)^2*Simulation!E16*Assumptions!$D$16)/(1+Simulation!K16)^3+(Assumptions!$D$14*(1+Simulation!E16)^4*F16-Assumptions!$D$14*(1+Simulation!E16)^3*Simulation!E16*Assumptions!$D$16)/(1+Simulation!K16)^4+(Assumptions!$D$14*(1+Simulation!E16)^5*F16-Assumptions!$D$14*(1+Simulation!E16)^4*Simulation!E16*Assumptions!$D$16)/(1+Simulation!K16)^5+(Assumptions!$D$14*(1+Simulation!E16)^5*F16-Assumptions!$D$14*(1+Simulation!E16)^4*Simulation!E16*Assumptions!$D$16)*(1+Simulation!I16)/(Simulation!K16-Simulation!I16)/(1+Simulation!K16)^5-Assumptions!$D$17)/Assumptions!$D$18 -> 11.40936 | H16: =IF(D16=1,G16,"") | I16: =IF(D16=0,G16,"") -> 11.40936 | K16: Value at stake in the event
B17: 12 | C17: =IF('Random Draws'!F17<(Assumptions!$D$28-Assumptions!$D$27)/(Assumptions!$D$29-Assumptions!$D$27),Assumptions!$D$27+SQRT('Random Draws'!F17*(Assumptions!$D$29-Assumptions!$D$27)*(Assumptions!$D$28-Assumptions!$D$27)),Assumptions!$D$29-SQRT((1-'Random Draws'!F17)*(Assumptions!$D$29-Assumptions!$D$27)*(Assumptions!$D$29-Assumptions!$D$28))) -> 0.25152771 | D17: =IF('Random Draws'!I17<Assumptions!$D$30,1,0) -> 0 | E17: =C17+Assumptions!$D$31*D17 -> 0.25152771 | F17: =(Simulation!F17-Assumptions!$D$15)*(1-E17)+Assumptions!$D$15-Simulation!J17 -> 0.21563632 | G17: =((Assumptions!$D$14*(1+Simulation!E17)^1*F17-Assumptions!$D$14*(1+Simulation!E17)^0*Simulation!E17*Assumptions!$D$16)/(1+Simulation!K17)^1+(Assumptions!$D$14*(1+Simulation!E17)^2*F17-Assumptions!$D$14*(1+Simulation!E17)^1*Simulation!E17*Assumptions!$D$16)/(1+Simulation!K17)^2+(Assumptions!$D$14*(1+Simulation!E17)^3*F17-Assumptions!$D$14*(1+Simulation!E17)^2*Simulation!E17*Assumptions!$D$16)/(1+Simulation!K17)^3+(Assumptions!$D$14*(1+Simulation!E17)^4*F17-Assumptions!$D$14*(1+Simulation!E17)^3*Simulation!E17*Assumptions!$D$16)/(1+Simulation!K17)^4+(Assumptions!$D$14*(1+Simulation!E17)^5*F17-Assumptions!$D$14*(1+Simulation!E17)^4*Simulation!E17*Assumptions!$D$16)/(1+Simulation!K17)^5+(Assumptions!$D$14*(1+Simulation!E17)^5*F17-Assumptions!$D$14*(1+Simulation!E17)^4*Simulation!E17*Assumptions!$D$16)*(1+Simulation!I17)/(Simulation!K17-Simulation!I17)/(1+Simulation!K17)^5-Assumptions!$D$17)/Assumptions!$D$18 -> 19.674221 | H17: =IF(D17=1,G17,"") | I17: =IF(D17=0,G17,"") -> 19.674221 | K17: Median gap, no surcharge minus surcharge | L17: =N7-M7 -> 3.5421306
B18: 13 | C18: =IF('Random Draws'!F18<(Assumptions!$D$28-Assumptions!$D$27)/(Assumptions!$D$29-Assumptions!$D$27),Assumptions!$D$27+SQRT('Random Draws'!F18*(Assumptions!$D$29-Assumptions!$D$27)*(Assumptions!$D$28-Assumptions!$D$27)),Assumptions!$D$29-SQRT((1-'Random Draws'!F18)*(Assumptions!$D$29-Assumptions!$D$27)*(Assumptions!$D$29-Assumptions!$D$28))) -> 0.24882673 | D18: =IF('Random Draws'!I18<Assumptions!$D$30,1,0) -> 0 | E18: =C18+Assumptions!$D$31*D18 -> 0.24882673 | F18: =(Simulation!F18-Assumptions!$D$15)*(1-E18)+Assumptions!$D$15-Simulation!J18 -> 0.21136636 | G18: =((Assumptions!$D$14*(1+Simulation!E18)^1*F18-Assumptions!$D$14*(1+Simulation!E18)^0*Simulation!E18*Assumptions!$D$16)/(1+Simulation!K18)^1+(Assumptions!$D$14*(1+Simulation!E18)^2*F18-Assumptions!$D$14*(1+Simulation!E18)^1*Simulation!E18*Assumptions!$D$16)/(1+Simulation!K18)^2+(Assumptions!$D$14*(1+Simulation!E18)^3*F18-Assumptions!$D$14*(1+Simulation!E18)^2*Simulation!E18*Assumptions!$D$16)/(1+Simulation!K18)^3+(Assumptions!$D$14*(1+Simulation!E18)^4*F18-Assumptions!$D$14*(1+Simulation!E18)^3*Simulation!E18*Assumptions!$D$16)/(1+Simulation!K18)^4+(Assumptions!$D$14*(1+Simulation!E18)^5*F18-Assumptions!$D$14*(1+Simulation!E18)^4*Simulation!E18*Assumptions!$D$16)/(1+Simulation!K18)^5+(Assumptions!$D$14*(1+Simulation!E18)^5*F18-Assumptions!$D$14*(1+Simulation!E18)^4*Simulation!E18*Assumptions!$D$16)*(1+Simulation!I18)/(Simulation!K18-Simulation!I18)/(1+Simulation!K18)^5-Assumptions!$D$17)/Assumptions!$D$18 -> 17.758386 | H18: =IF(D18=1,G18,"") | I18: =IF(D18=0,G18,"") -> 17.758386
B19: 14 | C19: =IF('Random Draws'!F19<(Assumptions!$D$28-Assumptions!$D$27)/(Assumptions!$D$29-Assumptions!$D$27),Assumptions!$D$27+SQRT('Random Draws'!F19*(Assumptions!$D$29-Assumptions!$D$27)*(Assumptions!$D$28-Assumptions!$D$27)),Assumptions!$D$29-SQRT((1-'Random Draws'!F19)*(Assumptions!$D$29-Assumptions!$D$27)*(Assumptions!$D$29-Assumptions!$D$28))) -> 0.26992119 | D19: =IF('Random Draws'!I19<Assumptions!$D$30,1,0) -> 0 | E19: =C19+Assumptions!$D$31*D19 -> 0.26992119 | F19: =(Simulation!F19-Assumptions!$D$15)*(1-E19)+Assumptions!$D$15-Simulation!J19 -> 0.12723371 | G19: =((Assumptions!$D$14*(1+Simulation!E19)^1*F19-Assumptions!$D$14*(1+Simulation!E19)^0*Simulation!E19*Assumptions!$D$16)/(1+Simulation!K19)^1+(Assumptions!$D$14*(1+Simulation!E19)^2*F19-Assumptions!$D$14*(1+Simulation!E19)^1*Simulation!E19*Assumptions!$D$16)/(1+Simulation!K19)^2+(Assumptions!$D$14*(1+Simulation!E19)^3*F19-Assumptions!$D$14*(1+Simulation!E19)^2*Simulation!E19*Assumptions!$D$16)/(1+Simulation!K19)^3+(Assumptions!$D$14*(1+Simulation!E19)^4*F19-Assumptions!$D$14*(1+Simulation!E19)^3*Simulation!E19*Assumptions!$D$16)/(1+Simulation!K19)^4+(Assumptions!$D$14*(1+Simulation!E19)^5*F19-Assumptions!$D$14*(1+Simulation!E19)^4*Simulation!E19*Assumptions!$D$16)/(1+Simulation!K19)^5+(Assumptions!$D$14*(1+Simulation!E19)^5*F19-Assumptions!$D$14*(1+Simulation!E19)^4*Simulation!E19*Assumptions!$D$16)*(1+Simulation!I19)/(Simulation!K19-Simulation!I19)/(1+Simulation!K19)^5-Assumptions!$D$17)/Assumptions!$D$18 -> 11.456442 | H19: =IF(D19=1,G19,"") | I19: =IF(D19=0,G19,"") -> 11.456442 | K19: Both models average about the same tax. The headline distribution barely moves; the event model shows that
B20: 15 | C20: =IF('Random Draws'!F20<(Assumptions!$D$28-Assumptions!$D$27)/(Assumptions!$D$29-Assumptions!$D$27),Assumptions!$D$27+SQRT('Random Draws'!F20*(Assumptions!$D$29-Assumptions!$D$27)*(Assumptions!$D$28-Assumptions!$D$27)),Assumptions!$D$29-SQRT((1-'Random Draws'!F20)*(Assumptions!$D$29-Assumptions!$D$27)*(Assumptions!$D$29-Assumptions!$D$28))) -> 0.27315152 | D20: =IF('Random Draws'!I20<Assumptions!$D$30,1,0) -> 0 | E20: =C20+Assumptions!$D$31*D20 -> 0.27315152 | F20: =(Simulation!F20-Assumptions!$D$15)*(1-E20)+Assumptions!$D$15-Simulation!J20 -> 0.19203265 | G20: =((Assumptions!$D$14*(1+Simulation!E20)^1*F20-Assumptions!$D$14*(1+Simulation!E20)^0*Simulation!E20*Assumptions!$D$16)/(1+Simulation!K20)^1+(Assumptions!$D$14*(1+Simulation!E20)^2*F20-Assumptions!$D$14*(1+Simulation!E20)^1*Simulation!E20*Assumptions!$D$16)/(1+Simulation!K20)^2+(Assumptions!$D$14*(1+Simulation!E20)^3*F20-Assumptions!$D$14*(1+Simulation!E20)^2*Simulation!E20*Assumptions!$D$16)/(1+Simulation!K20)^3+(Assumptions!$D$14*(1+Simulation!E20)^4*F20-Assumptions!$D$14*(1+Simulation!E20)^3*Simulation!E20*Assumptions!$D$16)/(1+Simulation!K20)^4+(Assumptions!$D$14*(1+Simulation!E20)^5*F20-Assumptions!$D$14*(1+Simulation!E20)^4*Simulation!E20*Assumptions!$D$16)/(1+Simulation!K20)^5+(Assumptions!$D$14*(1+Simulation!E20)^5*F20-Assumptions!$D$14*(1+Simulation!E20)^4*Simulation!E20*Assumptions!$D$16)*(1+Simulation!I20)/(Simulation!K20-Simulation!I20)/(1+Simulation!K20)^5-Assumptions!$D$17)/Assumptions!$D$18 -> 11.83539 | H20: =IF(D20=1,G20,"") | I20: =IF(D20=0,G20,"") -> 11.83539 | K20: about €3 of value per share rides on one political decision.
B21: 16 | C21: =IF('Random Draws'!F21<(Assumptions!$D$28-Assumptions!$D$27)/(Assumptions!$D$29-Assumptions!$D$27),Assumptions!$D$27+SQRT('Random Draws'!F21*(Assumptions!$D$29-Assumptions!$D$27)*(Assumptions!$D$28-Assumptions!$D$27)),Assumptions!$D$29-SQRT((1-'Random Draws'!F21)*(Assumptions!$D$29-Assumptions!$D$27)*(Assumptions!$D$29-Assumptions!$D$28))) -> 0.26076862 | D21: =IF('Random Draws'!I21<Assumptions!$D$30,1,0) -> 1 | E21: =C21+Assumptions!$D$31*D21 -> 0.35076862 | F21: =(Simulation!F21-Assumptions!$D$15)*(1-E21)+Assumptions!$D$15-Simulation!J21 -> 0.15652878 | G21: =((Assumptions!$D$14*(1+Simulation!E21)^1*F21-Assumptions!$D$14*(1+Simulation!E21)^0*Simulation!E21*Assumptions!$D$16)/(1+Simulation!K21)^1+(Assumptions!$D$14*(1+Simulation!E21)^2*F21-Assumptions!$D$14*(1+Simulation!E21)^1*Simulation!E21*Assumptions!$D$16)/(1+Simulation!K21)^2+(Assumptions!$D$14*(1+Simulation!E21)^3*F21-Assumptions!$D$14*(1+Simulation!E21)^2*Simulation!E21*Assumptions!$D$16)/(1+Simulation!K21)^3+(Assumptions!$D$14*(1+Simulation!E21)^4*F21-Assumptions!$D$14*(1+Simulation!E21)^3*Simulation!E21*Assumptions!$D$16)/(1+Simulation!K21)^4+(Assumptions!$D$14*(1+Simulation!E21)^5*F21-Assumptions!$D$14*(1+Simulation!E21)^4*Simulation!E21*Assumptions!$D$16)/(1+Simulation!K21)^5+(Assumptions!$D$14*(1+Simulation!E21)^5*F21-Assumptions!$D$14*(1+Simulation!E21)^4*Simulation!E21*Assumptions!$D$16)*(1+Simulation!I21)/(Simulation!K21-Simulation!I21)/(1+Simulation!K21)^5-Assumptions!$D$17)/Assumptions!$D$18 -> 8.255569 | H21: =IF(D21=1,G21,"") -> 8.255569 | I21: =IF(D21=0,G21,"")
B22: 17 | C22: =IF('Random Draws'!F22<(Assumptions!$D$28-Assumptions!$D$27)/(Assumptions!$D$29-Assumptions!$D$27),Assumptions!$D$27+SQRT('Random Draws'!F22*(Assumptions!$D$29-Assumptions!$D$27)*(Assumptions!$D$28-Assumptions!$D$27)),Assumptions!$D$29-SQRT((1-'Random Draws'!F22)*(Assumptions!$D$29-Assumptions!$D$27)*(Assumptions!$D$29-Assumptions!$D$28))) -> 0.2584659 | D22: =IF('Random Draws'!I22<Assumptions!$D$30,1,0) -> 0 | E22: =C22+Assumptions!$D$31*D22 -> 0.2584659 | F22: =(Simulation!F22-Assumptions!$D$15)*(1-E22)+Assumptions!$D$15-Simulation!J22 -> 0.16658899 | G22: =((Assumptions!$D$14*(1+Simulation!E22)^1*F22-Assumptions!$D$14*(1+Simulation!E22)^0*Simulation!E22*Assumptions!$D$16)/(1+Simulation!K22)^1+(Assumptions!$D$14*(1+Simulation!E22)^2*F22-Assumptions!$D$14*(1+Simulation!E22)^1*Simulation!E22*Assumptions!$D$16)/(1+Simulation!K22)^2+(Assumptions!$D$14*(1+Simulation!E22)^3*F22-Assumptions!$D$14*(1+Simulation!E22)^2*Simulation!E22*Assumptions!$D$16)/(1+Simulation!K22)^3+(Assumptions!$D$14*(1+Simulation!E22)^4*F22-Assumptions!$D$14*(1+Simulation!E22)^3*Simulation!E22*Assumptions!$D$16)/(1+Simulation!K22)^4+(Assumptions!$D$14*(1+Simulation!E22)^5*F22-Assumptions!$D$14*(1+Simulation!E22)^4*Simulation!E22*Assumptions!$D$16)/(1+Simulation!K22)^5+(Assumptions!$D$14*(1+Simulation!E22)^5*F22-Assumptions!$D$14*(1+Simulation!E22)^4*Simulation!E22*Assumptions!$D$16)*(1+Simulation!I22)/(Simulation!K22-Simulation!I22)/(1+Simulation!K22)^5-Assumptions!$D$17)/Assumptions!$D$18 -> 11.305867 | H22: =IF(D22=1,G22,"") | I22: =IF(D22=0,G22,"") -> 11.305867
B23: 18 | C23: =IF('Random Draws'!F23<(Assumptions!$D$28-Assumptions!$D$27)/(Assumptions!$D$29-Assumptions!$D$27),Assumptions!$D$27+SQRT('Random Draws'!F23*(Assumptions!$D$29-Assumptions!$D$27)*(Assumptions!$D$28-Assumptions!$D$27)),Assumptions!$D$29-SQRT((1-'Random Draws'!F23)*(Assumptions!$D$29-Assumptions!$D$27)*(Assumptions!$D$29-Assumptions!$D$28))) -> 0.25614022 | D23: =IF('Random Draws'!I23<Assumptions!$D$30,1,0) -> 0 | E23: =C23+Assumptions!$D$31*D23 -> 0.25614022 | F23: =(Simulation!F23-Assumptions!$D$15)*(1-E23)+Assumptions!$D$15-Simulation!J23 -> 0.20116475 | G23: =((Assumptions!$D$14*(1+Simulation!E23)^1*F23-Assumptions!$D$14*(1+Simulation!E23)^0*Simulation!E23*Assumptions!$D$16)/(1+Simulation!K23)^1+(Assumptions!$D$14*(1+Simulation!E23)^2*F23-Assumptions!$D$14*(1+Simulation!E23)^1*Simulation!E23*Assumptions!$D$16)/(1+Simulation!K23)^2+(Assumptions!$D$14*(1+Simulation!E23)^3*F23-Assumptions!$D$14*(1+Simulation!E23)^2*Simulation!E23*Assumptions!$D$16)/(1+Simulation!K23)^3+(Assumptions!$D$14*(1+Simulation!E23)^4*F23-Assumptions!$D$14*(1+Simulation!E23)^3*Simulation!E23*Assumptions!$D$16)/(1+Simulation!K23)^4+(Assumptions!$D$14*(1+Simulation!E23)^5*F23-Assumptions!$D$14*(1+Simulation!E23)^4*Simulation!E23*Assumptions!$D$16)/(1+Simulation!K23)^5+(Assumptions!$D$14*(1+Simulation!E23)^5*F23-Assumptions!$D$14*(1+Simulation!E23)^4*Simulation!E23*Assumptions!$D$16)*(1+Simulation!I23)/(Simulation!K23-Simulation!I23)/(1+Simulation!K23)^5-Assumptions!$D$17)/Assumptions!$D$18 -> 15.346572 | H23: =IF(D23=1,G23,"") | I23: =IF(D23=0,G23,"") -> 15.346572
B24: 19 | C24: =IF('Random Draws'!F24<(Assumptions!$D$28-Assumptions!$D$27)/(Assumptions!$D$29-Assumptions!$D$27),Assumptions!$D$27+SQRT('Random Draws'!F24*(Assumptions!$D$29-Assumptions!$D$27)*(Assumptions!$D$28-Assumptions!$D$27)),Assumptions!$D$29-SQRT((1-'Random Draws'!F24)*(Assumptions!$D$29-Assumptions!$D$27)*(Assumptions!$D$29-Assumptions!$D$28))) -> 0.27023286 | D24: =IF('Random Draws'!I24<Assumptions!$D$30,1,0) -> 0 | E24: =C24+Assumptions!$D$31*D24 -> 0.27023286 | F24: =(Simulation!F24-Assumptions!$D$15)*(1-E24)+Assumptions!$D$15-Simulation!J24 -> 0.20854487 | G24: =((Assumptions!$D$14*(1+Simulation!E24)^1*F24-Assumptions!$D$14*(1+Simulation!E24)^0*Simulation!E24*Assumptions!$D$16)/(1+Simulation!K24)^1+(Assumptions!$D$14*(1+Simulation!E24)^2*F24-Assumptions!$D$14*(1+Simulation!E24)^1*Simulation!E24*Assumptions!$D$16)/(1+Simulation!K24)^2+(Assumptions!$D$14*(1+Simulation!E24)^3*F24-Assumptions!$D$14*(1+Simulation!E24)^2*Simulation!E24*Assumptions!$D$16)/(1+Simulation!K24)^3+(Assumptions!$D$14*(1+Simulation!E24)^4*F24-Assumptions!$D$14*(1+Simulation!E24)^3*Simulation!E24*Assumptions!$D$16)/(1+Simulation!K24)^4+(Assumptions!$D$14*(1+Simulation!E24)^5*F24-Assumptions!$D$14*(1+Simulation!E24)^4*Simulation!E24*Assumptions!$D$16)/(1+Simulation!K24)^5+(Assumptions!$D$14*(1+Simulation!E24)^5*F24-Assumptions!$D$14*(1+Simulation!E24)^4*Simulation!E24*Assumptions!$D$16)*(1+Simulation!I24)/(Simulation!K24-Simulation!I24)/(1+Simulation!K24)^5-Assumptions!$D$17)/Assumptions!$D$18 -> 25.48854 | H24: =IF(D24=1,G24,"") | I24: =IF(D24=0,G24,"") -> 25.48854
B25: 20 | C25: =IF('Random Draws'!F25<(Assumptions!$D$28-Assumptions!$D$27)/(Assumptions!$D$29-Assumptions!$D$27),Assumptions!$D$27+SQRT('Random Draws'!F25*(Assumptions!$D$29-Assumptions!$D$27)*(Assumptions!$D$28-Assumptions!$D$27)),Assumptions!$D$29-SQRT((1-'Random Draws'!F25)*(Assumptions!$D$29-Assumptions!$D$27)*(Assumptions!$D$29-Assumptions!$D$28))) -> 0.26713904 | D25: =IF('Random Draws'!I25<Assumptions!$D$30,1,0) -> 0 | E25: =C25+Assumptions!$D$31*D25 -> 0.26713904 | F25: =(Simulation!F25-Assumptions!$D$15)*(1-E25)+Assumptions!$D$15-Simulation!J25 -> 0.17479243 | G25: =((Assumptions!$D$14*(1+Simulation!E25)^1*F25-Assumptions!$D$14*(1+Simulation!E25)^0*Simulation!E25*Assumptions!$D$16)/(1+Simulation!K25)^1+(Assumptions!$D$14*(1+Simulation!E25)^2*F25-Assumptions!$D$14*(1+Simulation!E25)^1*Simulation!E25*Assumptions!$D$16)/(1+Simulation!K25)^2+(Assumptions!$D$14*(1+Simulation!E25)^3*F25-Assumptions!$D$14*(1+Simulation!E25)^2*Simulation!E25*Assumptions!$D$16)/(1+Simulation!K25)^3+(Assumptions!$D$14*(1+Simulation!E25)^4*F25-Assumptions!$D$14*(1+Simulation!E25)^3*Simulation!E25*Assumptions!$D$16)/(1+Simulation!K25)^4+(Assumptions!$D$14*(1+Simulation!E25)^5*F25-Assumptions!$D$14*(1+Simulation!E25)^4*Simulation!E25*Assumptions!$D$16)/(1+Simulation!K25)^5+(Assumptions!$D$14*(1+Simulation!E25)^5*F25-Assumptions!$D$14*(1+Simulation!E25)^4*Simulation!E25*Assumptions!$D$16)*(1+Simulation!I25)/(Simulation!K25-Simulation!I25)/(1+Simulation!K25)^5-Assumptions!$D$17)/Assumptions!$D$18 -> 9.1538115 | H25: =IF(D25=1,G25,"") | I25: =IF(D25=0,G25,"") -> 9.1538115
B26: 21 | C26: =IF('Random Draws'!F26<(Assumptions!$D$28-Assumptions!$D$27)/(Assumptions!$D$29-Assumptions!$D$27),Assumptions!$D$27+SQRT('Random Draws'!F26*(Assumptions!$D$29-Assumptions!$D$27)*(Assumptions!$D$28-Assumptions!$D$27)),Assumptions!$D$29-SQRT((1-'Random Draws'!F26)*(Assumptions!$D$29-Assumptions!$D$27)*(Assumptions!$D$29-Assumptions!$D$28))) -> 0.24937137 | D26: =IF('Random Draws'!I26<Assumptions!$D$30,1,0) -> 0 | E26: =C26+Assumptions!$D$31*D26 -> 0.24937137 | F26: =(Simulation!F26-Assumptions!$D$15)*(1-E26)+Assumptions!$D$15-Simulation!J26 -> 0.12630266 | G26: =((Assumptions!$D$14*(1+Simulation!E26)^1*F26-Assumptions!$D$14*(1+Simulation!E26)^0*Simulation!E26*Assumptions!$D$16)/(1+Simulation!K26)^1+(Assumptions!$D$14*(1+Simulation!E26)^2*F26-Assumptions!$D$14*(1+Simulation!E26)^1*Simulation!E26*Assumptions!$D$16)/(1+Simulation!K26)^2+(Assumptions!$D$14*(1+Simulation!E26)^3*F26-Assumptions!$D$14*(1+Simulation!E26)^2*Simulation!E26*Assumptions!$D$16)/(1+Simulation!K26)^3+(Assumptions!$D$14*(1+Simulation!E26)^4*F26-Assumptions!$D$14*(1+Simulation!E26)^3*Simulation!E26*Assumptions!$D$16)/(1+Simulation!K26)^4+(Assumptions!$D$14*(1+Simulation!E26)^5*F26-Assumptions!$D$14*(1+Simulation!E26)^4*Simulation!E26*Assumptions!$D$16)/(1+Simulation!K26)^5+(Assumptions!$D$14*(1+Simulation!E26)^5*F26-Assumptions!$D$14*(1+Simulation!E26)^4*Simulation!E26*Assumptions!$D$16)*(1+Simulation!I26)/(Simulation!K26-Simulation!I26)/(1+Simulation!K26)^5-Assumptions!$D$17)/Assumptions!$D$18 -> 7.1882457 | H26: =IF(D26=1,G26,"") | I26: =IF(D26=0,G26,"") -> 7.1882457
B27: 22 | C27: =IF('Random Draws'!F27<(Assumptions!$D$28-Assumptions!$D$27)/(Assumptions!$D$29-Assumptions!$D$27),Assumptions!$D$27+SQRT('Random Draws'!F27*(Assumptions!$D$29-Assumptions!$D$27)*(Assumptions!$D$28-Assumptions!$D$27)),Assumptions!$D$29-SQRT((1-'Random Draws'!F27)*(Assumptions!$D$29-Assumptions!$D$27)*(Assumptions!$D$29-Assumptions!$D$28))) -> 0.26114444 | D27: =IF('Random Draws'!I27<Assumptions!$D$30,1,0) -> 0 | E27: =C27+Assumptions!$D$31*D27 -> 0.26114444 | F27: =(Simulation!F27-Assumptions!$D$15)*(1-E27)+Assumptions!$D$15-Simulation!J27 -> 0.18512249 | G27: =((Assumptions!$D$14*(1+Simulation!E27)^1*F27-Assumptions!$D$14*(1+Simulation!E27)^0*Simulation!E27*Assumptions!$D$16)/(1+Simulation!K27)^1+(Assumptions!$D$14*(1+Simulation!E27)^2*F27-Assumptions!$D$14*(1+Simulation!E27)^1*Simulation!E27*Assumptions!$D$16)/(1+Simulation!K27)^2+(Assumptions!$D$14*(1+Simulation!E27)^3*F27-Assumptions!$D$14*(1+Simulation!E27)^2*Simulation!E27*Assumptions!$D$16)/(1+Simulation!K27)^3+(Assumptions!$D$14*(1+Simulation!E27)^4*F27-Assumptions!$D$14*(1+Simulation!E27)^3*Simulation!E27*Assumptions!$D$16)/(1+Simulation!K27)^4+(Assumptions!$D$14*(1+Simulation!E27)^5*F27-Assumptions!$D$14*(1+Simulation!E27)^4*Simulation!E27*Assumptions!$D$16)/(1+Simulation!K27)^5+(Assumptions!$D$14*(1+Simulation!E27)^5*F27-Assumptions!$D$14*(1+Simulation!E27)^4*Simulation!E27*Assumptions!$D$16)*(1+Simulation!I27)/(Simulation!K27-Simulation!I27)/(1+Simulation!K27)^5-Assumptions!$D$17)/Assumptions!$D$18 -> 11.566505 | H27: =IF(D27=1,G27,"") | I27: =IF(D27=0,G27,"") -> 11.566505
B28: 23 | C28: =IF('Random Draws'!F28<(Assumptions!$D$28-Assumptions!$D$27)/(Assumptions!$D$29-Assumptions!$D$27),Assumptions!$D$27+SQRT('Random Draws'!F28*(Assumptions!$D$29-Assumptions!$D$27)*(Assumptions!$D$28-Assumptions!$D$27)),Assumptions!$D$29-SQRT((1-'Random Draws'!F28)*(Assumptions!$D$29-Assumptions!$D$27)*(Assumptions!$D$29-Assumptions!$D$28))) -> 0.2649791 | D28: =IF('Random Draws'!I28<Assumptions!$D$30,1,0) -> 1 | E28: =C28+Assumptions!$D$31*D28 -> 0.3549791 | F28: =(Simulation!F28-Assumptions!$D$15)*(1-E28)+Assumptions!$D$15-Simulation!J28 -> 0.11955818 | G28: =((Assumptions!$D$14*(1+Simulation!E28)^1*F28-Assumptions!$D$14*(1+Simulation!E28)^0*Simulation!E28*Assumptions!$D$16)/(1+Simulation!K28)^1+(Assumptions!$D$14*(1+Simulation!E28)^2*F28-Assumptions!$D$14*(1+Simulation!E28)^1*Simulation!E28*Assumptions!$D$16)/(1+Simulation!K28)^2+(Assumptions!$D$14*(1+Simulation!E28)^3*F28-Assumptions!$D$14*(1+Simulation!E28)^2*Simulation!E28*Assumptions!$D$16)/(1+Simulation!K28)^3+(Assumptions!$D$14*(1+Simulation!E28)^4*F28-Assumptions!$D$14*(1+Simulation!E28)^3*Simulation!E28*Assumptions!$D$16)/(1+Simulation!K28)^4+(Assumptions!$D$14*(1+Simulation!E28)^5*F28-Assumptions!$D$14*(1+Simulation!E28)^4*Simulation!E28*Assumptions!$D$16)/(1+Simulation!K28)^5+(Assumptions!$D$14*(1+Simulation!E28)^5*F28-Assumptions!$D$14*(1+Simulation!E28)^4*Simulation!E28*Assumptions!$D$16)*(1+Simulation!I28)/(Simulation!K28-Simulation!I28)/(1+Simulation!K28)^5-Assumptions!$D$17)/Assumptions!$D$18 -> 11.875721 | H28: =IF(D28=1,G28,"") -> 11.875721 | I28: =IF(D28=0,G28,"")
B29: 24 | C29: =IF('Random Draws'!F29<(Assumptions!$D$28-Assumptions!$D$27)/(Assumptions!$D$29-Assumptions!$D$27),Assumptions!$D$27+SQRT('Random Draws'!F29*(Assumptions!$D$29-Assumptions!$D$27)*(Assumptions!$D$28-Assumptions!$D$27)),Assumptions!$D$29-SQRT((1-'Random Draws'!F29)*(Assumptions!$D$29-Assumptions!$D$27)*(Assumptions!$D$29-Assumptions!$D$28))) -> 0.24735723 | D29: =IF('Random Draws'!I29<Assumptions!$D$30,1,0) -> 1 | E29: =C29+Assumptions!$D$31*D29 -> 0.33735723 | F29: =(Simulation!F29-Assumptions!$D$15)*(1-E29)+Assumptions!$D$15-Simulation!J29 -> 0.11762543 | G29: =((Assumptions!$D$14*(1+Simulation!E29)^1*F29-Assumptions!$D$14*(1+Simulation!E29)^0*Simulation!E29*Assumptions!$D$16)/(1+Simulation!K29)^1+(Assumptions!$D$14*(1+Simulation!E29)^2*F29-Assumptions!$D$14*(1+Simulation!E29)^1*Simulation!E29*Assumptions!$D$16)/(1+Simulation!K29)^2+(Assumptions!$D$14*(1+Simulation!E29)^3*F29-Assumptions!$D$14*(1+Simulation!E29)^2*Simulation!E29*Assumptions!$D$16)/(1+Simulation!K29)^3+(Assumptions!$D$14*(1+Simulation!E29)^4*F29-Assumptions!$D$14*(1+Simulation!E29)^3*Simulation!E29*Assumptions!$D$16)/(1+Simulation!K29)^4+(Assumptions!$D$14*(1+Simulation!E29)^5*F29-Assumptions!$D$14*(1+Simulation!E29)^4*Simulation!E29*Assumptions!$D$16)/(1+Simulation!K29)^5+(Assumptions!$D$14*(1+Simulation!E29)^5*F29-Assumptions!$D$14*(1+Simulation!E29)^4*Simulation!E29*Assumptions!$D$16)*(1+Simulation!I29)/(Simulation!K29-Simulation!I29)/(1+Simulation!K29)^5-Assumptions!$D$17)/Assumptions!$D$18 -> 10.024572 | H29: =IF(D29=1,G29,"") -> 10.024572 | I29: =IF(D29=0,G29,"")
B30: 25 | C30: =IF('Random Draws'!F30<(Assumptions!$D$28-Assumptions!$D$27)/(Assumptions!$D$29-Assumptions!$D$27),Assumptions!$D$27+SQRT('Random Draws'!F30*(Assumptions!$D$29-Assumptions!$D$27)*(Assumptions!$D$28-Assumptions!$D$27)),Assumptions!$D$29-SQRT((1-'Random Draws'!F30)*(Assumptions!$D$29-Assumptions!$D$27)*(Assumptions!$D$29-Assumptions!$D$28))) -> 0.25309146 | D30: =IF('Random Draws'!I30<Assumptions!$D$30,1,0) -> 0 | E30: =C30+Assumptions!$D$31*D30 -> 0.25309146 | F30: =(Simulation!F30-Assumptions!$D$15)*(1-E30)+Assumptions!$D$15-Simulation!J30 -> 0.19590376 | G30: =((Assumptions!$D$14*(1+Simulation!E30)^1*F30-Assumptions!$D$14*(1+Simulation!E30)^0*Simulation!E30*Assumptions!$D$16)/(1+Simulation!K30)^1+(Assumptions!$D$14*(1+Simulation!E30)^2*F30-Assumptions!$D$14*(1+Simulation!E30)^1*Simulation!E30*Assumptions!$D$16)/(1+Simulation!K30)^2+(Assumptions!$D$14*(1+Simulation!E30)^3*F30-Assumptions!$D$14*(1+Simulation!E30)^2*Simulation!E30*Assumptions!$D$16)/(1+Simulation!K30)^3+(Assumptions!$D$14*(1+Simulation!E30)^4*F30-Assumptions!$D$14*(1+Simulation!E30)^3*Simulation!E30*Assumptions!$D$16)/(1+Simulation!K30)^4+(Assumptions!$D$14*(1+Simulation!E30)^5*F30-Assumptions!$D$14*(1+Simulation!E30)^4*Simulation!E30*Assumptions!$D$16)/(1+Simulation!K30)^5+(Assumptions!$D$14*(1+Simulation!E30)^5*F30-Assumptions!$D$14*(1+Simulation!E30)^4*Simulation!E30*Assumptions!$D$16)*(1+Simulation!I30)/(Simulation!K30-Simulation!I30)/(1+Simulation!K30)^5-Assumptions!$D$17)/Assumptions!$D$18 -> 15.375096 | H30: =IF(D30=1,G30,"") | I30: =IF(D30=0,G30,"") -> 15.375096
B31: 26 | C31: =IF('Random Draws'!F31<(Assumptions!$D$28-Assumptions!$D$27)/(Assumptions!$D$29-Assumptions!$D$27),Assumptions!$D$27+SQRT('Random Draws'!F31*(Assumptions!$D$29-Assumptions!$D$27)*(Assumptions!$D$28-Assumptions!$D$27)),Assumptions!$D$29-SQRT((1-'Random Draws'!F31)*(Assumptions!$D$29-Assumptions!$D$27)*(Assumptions!$D$29-Assumptions!$D$28))) -> 0.25490314 | D31: =IF('Random Draws'!I31<Assumptions!$D$30,1,0) -> 1 | E31: =C31+Assumptions!$D$31*D31 -> 0.34490314 | F31: =(Simulation!F31-Assumptions!$D$15)*(1-E31)+Assumptions!$D$15-Simulation!J31 -> 0.17085194 | G31: =((Assumptions!$D$14*(1+Simulation!E31)^1*F31-Assumptions!$D$14*(1+Simulation!E31)^0*Simulation!E31*Assumptions!$D$16)/(1+Simulation!K31)^1+(Assumptions!$D$14*(1+Simulation!E31)^2*F31-Assumptions!$D$14*(1+Simulation!E31)^1*Simulation!E31*Assumptions!$D$16)/(1+Simulation!K31)^2+(Assumptions!$D$14*(1+Simulation!E31)^3*F31-Assumptions!$D$14*(1+Simulation!E31)^2*Simulation!E31*Assumptions!$D$16)/(1+Simulation!K31)^3+(Assumptions!$D$14*(1+Simulation!E31)^4*F31-Assumptions!$D$14*(1+Simulation!E31)^3*Simulation!E31*Assumptions!$D$16)/(1+Simulation!K31)^4+(Assumptions!$D$14*(1+Simulation!E31)^5*F31-Assumptions!$D$14*(1+Simulation!E31)^4*Simulation!E31*Assumptions!$D$16)/(1+Simulation!K31)^5+(Assumptions!$D$14*(1+Simulation!E31)^5*F31-Assumptions!$D$14*(1+Simulation!E31)^4*Simulation!E31*Assumptions!$D$16)*(1+Simulation!I31)/(Simulation!K31-Simulation!I31)/(1+Simulation!K31)^5-Assumptions!$D$17)/Assumptions!$D$18 -> 18.539419 | H31: =IF(D31=1,G31,"") -> 18.539419 | I31: =IF(D31=0,G31,"")
B32: 27 | C32: =IF('Random Draws'!F32<(Assumptions!$D$28-Assumptions!$D$27)/(Assumptions!$D$29-Assumptions!$D$27),Assumptions!$D$27+SQRT('Random Draws'!F32*(Assumptions!$D$29-Assumptions!$D$27)*(Assumptions!$D$28-Assumptions!$D$27)),Assumptions!$D$29-SQRT((1-'Random Draws'!F32)*(Assumptions!$D$29-Assumptions!$D$27)*(Assumptions!$D$29-Assumptions!$D$28))) -> 0.26419094 | D32: =IF('Random Draws'!I32<Assumptions!$D$30,1,0) -> 0 | E32: =C32+Assumptions!$D$31*D32 -> 0.26419094 | F32: =(Simulation!F32-Assumptions!$D$15)*(1-E32)+Assumptions!$D$15-Simulation!J32 -> 0.19217057 | G32: =((Assumptions!$D$14*(1+Simulation!E32)^1*F32-Assumptions!$D$14*(1+Simulation!E32)^0*Simulation!E32*Assumptions!$D$16)/(1+Simulation!K32)^1+(Assumptions!$D$14*(1+Simulation!E32)^2*F32-Assumptions!$D$14*(1+Simulation!E32)^1*Simulation!E32*Assumptions!$D$16)/(1+Simulation!K32)^2+(Assumptions!$D$14*(1+Simulation!E32)^3*F32-Assumptions!$D$14*(1+Simulation!E32)^2*Simulation!E32*Assumptions!$D$16)/(1+Simulation!K32)^3+(Assumptions!$D$14*(1+Simulation!E32)^4*F32-Assumptions!$D$14*(1+Simulation!E32)^3*Simulation!E32*Assumptions!$D$16)/(1+Simulation!K32)^4+(Assumptions!$D$14*(1+Simulation!E32)^5*F32-Assumptions!$D$14*(1+Simulation!E32)^4*Simulation!E32*Assumptions!$D$16)/(1+Simulation!K32)^5+(Assumptions!$D$14*(1+Simulation!E32)^5*F32-Assumptions!$D$14*(1+Simulation!E32)^4*Simulation!E32*Assumptions!$D$16)*(1+Simulation!I32)/(Simulation!K32-Simulation!I32)/(1+Simulation!K32)^5-Assumptions!$D$17)/Assumptions!$D$18 -> 23.657236 | H32: =IF(D32=1,G32,"") | I32: =IF(D32=0,G32,"") -> 23.657236
... B2005: 2000 | C2005: =IF('Random Draws'!F2005<(Assumptions!$D$28-Assumptions!$D$27)/(Assumptions!$D$29-Assumptions!$D$27),Assumptions!$D$27+SQRT('Random Draws'!F2005*(Assumptions!$D$29-Assumptions!$D$27)*(Assumptions!$D$28-Assumptions!$D$27)),Assumptions!$D$29-SQRT((1-'Random Draws'!F2005)*(Assumptions!$D$29-Assumptions!$D$27)*(Assumptions!$D$29-Assumptions!$D$28))) -> 0.2458339 | D2005: =IF('Random Draws'!I2005<Assumptions!$D$30,1,0) -> 1 | E2005: =C2005+Assumptions!$D$31*D2005 -> 0.3358339 | F2005: =(Simulation!F2005-Assumptions!$D$15)*(1-E2005)+Assumptions!$D$15-Simulation!J2005 -> 0.19666455 | G2005: =((Assumptions!$D$14*(1+Simulation!E2005)^1*F2005-Assumptions!$D$14*(1+Simulation!E2005)^0*Simulation!E2005*Assumptions!$D$16)/(1+Simulation!K2005)^1+(Assumptions!$D$14*(1+Simulation!E2005)^2*F2005-Assumptions!$D$14*(1+Simulation!E2005)^1*Simulation!E2005*Assumptions!$D$16)/(1+Simulation!K2005)^2+(Assumptions!$D$14*(1+Simulation!E2005)^3*F2005-Assumptions!$D$14*(1+Simulation!E2005)^2*Simulation!E2005*Assumptions!$D$16)/(1+Simulation!K2005)^3+(Assumptions!$D$14*(1+Simulation!E2005)^4*F2005-Assumptions!$D$14*(1+Simulation!E2005)^3*Simulation!E2005*Assumptions!$D$16)/(1+Simulation!K2005)^4+(Assumptions!$D$14*(1+Simulation!E2005)^5*F2005-Assumptions!$D$14*(1+Simulation!E2005)^4*Simulation!E2005*Assumptions!$D$16)/(1+Simulation!K2005)^5+(Assumptions!$D$14*(1+Simulation!E2005)^5*F2005-Assumptions!$D$14*(1+Simulation!E2005)^4*Simulation!E2005*Assumptions!$D$16)*(1+Simulation!I2005)/(Simulation!K2005-Simulation!I2005)/(1+Simulation!K2005)^5-Assumptions!$D$17)/Assumptions!$D$18 -> 21.549893 | H2005: =IF(D2005=1,G2005,"") -> 21.549893 | I2005: =IF(D2005=0,G2005,"")

Sheet Convergence
B2: Convergence
B3: The whole simulation re-run 200 times with fresh random numbers at each size (Python); spread of the results across runs
B5: Iterations | C5: Average median | D5: Median, st. dev. | E5: Median, 2.5th pct | F5: Median, 97.5th pct | G5: P5, st. dev. | H5: P95, st. dev. | I5: P(> market), st. dev.
B6: 250 | C6: 12.565945 | D6: 0.43060242 | E6: 11.752205 | F6: 13.366247 | G6: 0.41430965 | H6: 1.0976288 | I6: 0.030831629
B7: 500 | C7: 12.558084 | D7: 0.30622483 | E7: 11.912723 | F7: 13.126573 | G7: 0.3725619 | H7: 0.87860457 | I7: 0.022966736
B8: 1000 | C8: 12.542088 | D8: 0.21372738 | E8: 12.151701 | F8: 12.92724 | G8: 0.22134854 | H8: 0.65603603 | I8: 0.016181812
B9: 2000 | C9: 12.514352 | D9: 0.1405274 | E9: 12.27113 | F9: 12.78663 | G9: 0.17430399 | H9: 0.45915082 | I9: 0.010253667
B10: 5000 | C10: 12.531343 | D10: 0.094497596 | E10: 12.361397 | F10: 12.720788 | G10: 0.10482691 | H10: 0.25233824 | I10: 0.0071449368
B11: 10000 | C11: 12.521402 | D11: 0.06857307 | E11: 12.402463 | F11: 12.643522 | G11: 0.076393571 | H11: 0.17701608 | I11: 0.005083256
B12: 25000 | C12: 12.519651 | D12: 0.0417946 | E12: 12.440383 | F12: 12.596003 | G12: 0.043793387 | H12: 0.13090832 | I12: 0.0030239177
B13: 50000 | C13: 12.517035 | D13: 0.03107907 | E13: 12.45606 | F13: 12.581595 | G13: 0.032607506 | H13: 0.090113207 | I13: 0.002245088
B15: This workbook
B16: Live median | C16: =Results!C7 -> 12.553903
B17: Inside the 95% band? | C17: =IF(AND(C16>=E9,C16<=F9),"Yes","No") -> Yes
B19: The spread of the median falls with the square root of the iterations: four times the runs halve it. The tails converge more slowly than the centre.

Sheet Price Paths
B2: Share-price paths
B3: Geometric Brownian Motion, monthly steps, from the market price; the shocks are fixed normals (rows 70 onwards)
B5: Start price (€) | C5: =Assumptions!$D$19 -> 11.5
B6: Annual drift | C6: 0.07
B7: Annual volatility | C7: 0.38
B8: Step (years) | C8: =Assumptions!$D$20/60 -> 0.083333333
B10: Path / month | C10: 0 | D10: 1 | E10: 2 | F10: 3 | G10: 4 | H10: 5 | I10: 6 | J10: 7 | K10: 8 | L10: 9 | M10: 10 | N10: 11 | O10: 12 | P10: 13 | Q10: 14 | R10: 15 | S10: 16 | T10: 17 | U10: 18 | V10: 19 | W10: 20 | X10: 21 | Y10: 22 | Z10: 23 | AA10: 24 | AB10: 25 | AC10: 26 | AD10: 27 | AE10: 28 | AF10: 29 | AG10: 30 | AH10: 31 | AI10: 32 | AJ10: 33 | AK10: 34 | AL10: 35 | AM10: 36 | AN10: 37 | AO10: 38 | AP10: 39 | AQ10: 40 | AR10: 41 | AS10: 42 | AT10: 43 | AU10: 44 | AV10: 45 | AW10: 46 | AX10: 47 | AY10: 48 | AZ10: 49 | BA10: 50 | BB10: 51 | BC10: 52 | BD10: 53 | BE10: 54 | BF10: 55 | BG10: 56 | BH10: 57 | BI10: 58 | BJ10: 59 | BK10: 60
B11: Path 1 | C11: =$C$5 -> 11.5 | D11: =C11*EXP(($C$6-0.5*$C$7^2)*$C$8+$C$7*SQRT($C$8)*D70) -> 11.499444 | E11: =D11*EXP(($C$6-0.5*$C$7^2)*$C$8+$C$7*SQRT($C$8)*E70) -> 11.880361 | F11: =E11*EXP(($C$6-0.5*$C$7^2)*$C$8+$C$7*SQRT($C$8)*F70) -> 11.5263 | G11: =F11*EXP(($C$6-0.5*$C$7^2)*$C$8+$C$7*SQRT($C$8)*G70) -> 10.45158 | H11: =G11*EXP(($C$6-0.5*$C$7^2)*$C$8+$C$7*SQRT($C$8)*H70) -> 9.9412625 | I11: =H11*EXP(($C$6-0.5*$C$7^2)*$C$8+$C$7*SQRT($C$8)*I70) -> 8.9149575 | J11: =I11*EXP(($C$6-0.5*$C$7^2)*$C$8+$C$7*SQRT($C$8)*J70) -> 8.9723237 | K11: =J11*EXP(($C$6-0.5*$C$7^2)*$C$8+$C$7*SQRT($C$8)*K70) -> 10.391398 | ... BK11: =BJ11*EXP(($C$6-0.5*$C$7^2)*$C$8+$C$7*SQRT($C$8)*BK70) -> 2.8675801
B12: Path 2 | C12: =$C$5 -> 11.5 | D12: =C12*EXP(($C$6-0.5*$C$7^2)*$C$8+$C$7*SQRT($C$8)*D71) -> 11.756982 | E12: =D12*EXP(($C$6-0.5*$C$7^2)*$C$8+$C$7*SQRT($C$8)*E71) -> 11.172336 | F12: =E12*EXP(($C$6-0.5*$C$7^2)*$C$8+$C$7*SQRT($C$8)*F71) -> 11.327329 | G12: =F12*EXP(($C$6-0.5*$C$7^2)*$C$8+$C$7*SQRT($C$8)*G71) -> 9.9423541 | H12: =G12*EXP(($C$6-0.5*$C$7^2)*$C$8+$C$7*SQRT($C$8)*H71) -> 9.3284895 | I12: =H12*EXP(($C$6-0.5*$C$7^2)*$C$8+$C$7*SQRT($C$8)*I71) -> 9.1281929 | J12: =I12*EXP(($C$6-0.5*$C$7^2)*$C$8+$C$7*SQRT($C$8)*J71) -> 10.072165 | K12: =J12*EXP(($C$6-0.5*$C$7^2)*$C$8+$C$7*SQRT($C$8)*K71) -> 11.418322 | ... BK12: =BJ12*EXP(($C$6-0.5*$C$7^2)*$C$8+$C$7*SQRT($C$8)*BK71) -> 6.5648449
B13: Path 3 | C13: =$C$5 -> 11.5 | D13: =C13*EXP(($C$6-0.5*$C$7^2)*$C$8+$C$7*SQRT($C$8)*D72) -> 11.611086 | E13: =D13*EXP(($C$6-0.5*$C$7^2)*$C$8+$C$7*SQRT($C$8)*E72) -> 10.880185 | F13: =E13*EXP(($C$6-0.5*$C$7^2)*$C$8+$C$7*SQRT($C$8)*F72) -> 10.73757 | G13: =F13*EXP(($C$6-0.5*$C$7^2)*$C$8+$C$7*SQRT($C$8)*G72) -> 8.6228838 | H13: =G13*EXP(($C$6-0.5*$C$7^2)*$C$8+$C$7*SQRT($C$8)*H72) -> 7.6150362 | I13: =H13*EXP(($C$6-0.5*$C$7^2)*$C$8+$C$7*SQRT($C$8)*I72) -> 7.9227921 | J13: =I13*EXP(($C$6-0.5*$C$7^2)*$C$8+$C$7*SQRT($C$8)*J72) -> 6.2718031 | K13: =J13*EXP(($C$6-0.5*$C$7^2)*$C$8+$C$7*SQRT($C$8)*K72) -> 6.8809078 | ... BK13: =BJ13*EXP(($C$6-0.5*$C$7^2)*$C$8+$C$7*SQRT($C$8)*BK72) -> 2.3758403
B14: Path 4 | C14: =$C$5 -> 11.5 | D14: =C14*EXP(($C$6-0.5*$C$7^2)*$C$8+$C$7*SQRT($C$8)*D73) -> 10.954733 | E14: =D14*EXP(($C$6-0.5*$C$7^2)*$C$8+$C$7*SQRT($C$8)*E73) -> 10.359114 | F14: =E14*EXP(($C$6-0.5*$C$7^2)*$C$8+$C$7*SQRT($C$8)*F73) -> 11.098403 | G14: =F14*EXP(($C$6-0.5*$C$7^2)*$C$8+$C$7*SQRT($C$8)*G73) -> 10.734943 | H14: =G14*EXP(($C$6-0.5*$C$7^2)*$C$8+$C$7*SQRT($C$8)*H73) -> 10.556142 | I14: =H14*EXP(($C$6-0.5*$C$7^2)*$C$8+$C$7*SQRT($C$8)*I73) -> 10.579966 | J14: =I14*EXP(($C$6-0.5*$C$7^2)*$C$8+$C$7*SQRT($C$8)*J73) -> 12.035225 | K14: =J14*EXP(($C$6-0.5*$C$7^2)*$C$8+$C$7*SQRT($C$8)*K73) -> 12.965658 | ... BK14: =BJ14*EXP(($C$6-0.5*$C$7^2)*$C$8+$C$7*SQRT($C$8)*BK73) -> 7.4770008
B15: Path 5 | C15: =$C$5 -> 11.5 | D15: =C15*EXP(($C$6-0.5*$C$7^2)*$C$8+$C$7*SQRT($C$8)*D74) -> 10.931866 | E15: =D15*EXP(($C$6-0.5*$C$7^2)*$C$8+$C$7*SQRT($C$8)*E74) -> 11.858262 | F15: =E15*EXP(($C$6-0.5*$C$7^2)*$C$8+$C$7*SQRT($C$8)*F74) -> 11.749303 | G15: =F15*EXP(($C$6-0.5*$C$7^2)*$C$8+$C$7*SQRT($C$8)*G74) -> 11.852064 | H15: =G15*EXP(($C$6-0.5*$C$7^2)*$C$8+$C$7*SQRT($C$8)*H74) -> 11.477953 | I15: =H15*EXP(($C$6-0.5*$C$7^2)*$C$8+$C$7*SQRT($C$8)*I74) -> 13.025344 | J15: =I15*EXP(($C$6-0.5*$C$7^2)*$C$8+$C$7*SQRT($C$8)*J74) -> 12.992318 | K15: =J15*EXP(($C$6-0.5*$C$7^2)*$C$8+$C$7*SQRT($C$8)*K74) -> 10.204174 | ... BK15: =BJ15*EXP(($C$6-0.5*$C$7^2)*$C$8+$C$7*SQRT($C$8)*BK74) -> 7.4249721
B16: Path 6 | C16: =$C$5 -> 11.5 | D16: =C16*EXP(($C$6-0.5*$C$7^2)*$C$8+$C$7*SQRT($C$8)*D75) -> 13.571964 | E16: =D16*EXP(($C$6-0.5*$C$7^2)*$C$8+$C$7*SQRT($C$8)*E75) -> 14.422362 | F16: =E16*EXP(($C$6-0.5*$C$7^2)*$C$8+$C$7*SQRT($C$8)*F75) -> 14.327542 | G16: =F16*EXP(($C$6-0.5*$C$7^2)*$C$8+$C$7*SQRT($C$8)*G75) -> 13.442792 | H16: =G16*EXP(($C$6-0.5*$C$7^2)*$C$8+$C$7*SQRT($C$8)*H75) -> 12.535976 | I16: =H16*EXP(($C$6-0.5*$C$7^2)*$C$8+$C$7*SQRT($C$8)*I75) -> 14.942813 | J16: =I16*EXP(($C$6-0.5*$C$7^2)*$C$8+$C$7*SQRT($C$8)*J75) -> 15.793982 | K16: =J16*EXP(($C$6-0.5*$C$7^2)*$C$8+$C$7*SQRT($C$8)*K75) -> 15.908534 | ... BK16: =BJ16*EXP(($C$6-0.5*$C$7^2)*$C$8+$C$7*SQRT($C$8)*BK75) -> 14.968856
B17: Path 7 | C17: =$C$5 -> 11.5 | D17: =C17*EXP(($C$6-0.5*$C$7^2)*$C$8+$C$7*SQRT($C$8)*D76) -> 12.150839 | E17: =D17*EXP(($C$6-0.5*$C$7^2)*$C$8+$C$7*SQRT($C$8)*E76) -> 14.916135 | F17: =E17*EXP(($C$6-0.5*$C$7^2)*$C$8+$C$7*SQRT($C$8)*F76) -> 15.913972 | G17: =F17*EXP(($C$6-0.5*$C$7^2)*$C$8+$C$7*SQRT($C$8)*G76) -> 16.008765 | H17: =G17*EXP(($C$6-0.5*$C$7^2)*$C$8+$C$7*SQRT($C$8)*H76) -> 13.303027 | I17: =H17*EXP(($C$6-0.5*$C$7^2)*$C$8+$C$7*SQRT($C$8)*I76) -> 13.878847 | J17: =I17*EXP(($C$6-0.5*$C$7^2)*$C$8+$C$7*SQRT($C$8)*J76) -> 11.208121 | K17: =J17*EXP(($C$6-0.5*$C$7^2)*$C$8+$C$7*SQRT($C$8)*K76) -> 9.6012097 | ... BK17: =BJ17*EXP(($C$6-0.5*$C$7^2)*$C$8+$C$7*SQRT($C$8)*BK76) -> 9.3393197
B18: Path 8 | C18: =$C$5 -> 11.5 | D18: =C18*EXP(($C$6-0.5*$C$7^2)*$C$8+$C$7*SQRT($C$8)*D77) -> 11.70641 | E18: =D18*EXP(($C$6-0.5*$C$7^2)*$C$8+$C$7*SQRT($C$8)*E77) -> 9.743609 | F18: =E18*EXP(($C$6-0.5*$C$7^2)*$C$8+$C$7*SQRT($C$8)*F77) -> 9.3411469 | G18: =F18*EXP(($C$6-0.5*$C$7^2)*$C$8+$C$7*SQRT($C$8)*G77) -> 10.403687 | H18: =G18*EXP(($C$6-0.5*$C$7^2)*$C$8+$C$7*SQRT($C$8)*H77) -> 9.0672128 | I18: =H18*EXP(($C$6-0.5*$C$7^2)*$C$8+$C$7*SQRT($C$8)*I77) -> 10.197078 | J18: =I18*EXP(($C$6-0.5*$C$7^2)*$C$8+$C$7*SQRT($C$8)*J77) -> 10.579432 | K18: =J18*EXP(($C$6-0.5*$C$7^2)*$C$8+$C$7*SQRT($C$8)*K77) -> 9.4329661 | ... BK18: =BJ18*EXP(($C$6-0.5*$C$7^2)*$C$8+$C$7*SQRT($C$8)*BK77) -> 1.3328331
B19: Path 9 | C19: =$C$5 -> 11.5 | D19: =C19*EXP(($C$6-0.5*$C$7^2)*$C$8+$C$7*SQRT($C$8)*D78) -> 11.809713 | E19: =D19*EXP(($C$6-0.5*$C$7^2)*$C$8+$C$7*SQRT($C$8)*E78) -> 11.7674 | F19: =E19*EXP(($C$6-0.5*$C$7^2)*$C$8+$C$7*SQRT($C$8)*F78) -> 11.973512 | G19: =F19*EXP(($C$6-0.5*$C$7^2)*$C$8+$C$7*SQRT($C$8)*G78) -> 12.036745 | H19: =G19*EXP(($C$6-0.5*$C$7^2)*$C$8+$C$7*SQRT($C$8)*H78) -> 14.836725 | I19: =H19*EXP(($C$6-0.5*$C$7^2)*$C$8+$C$7*SQRT($C$8)*I78) -> 13.2362 | J19: =I19*EXP(($C$6-0.5*$C$7^2)*$C$8+$C$7*SQRT($C$8)*J78) -> 11.155403 | K19: =J19*EXP(($C$6-0.5*$C$7^2)*$C$8+$C$7*SQRT($C$8)*K78) -> 9.9814876 | ... BK19: =BJ19*EXP(($C$6-0.5*$C$7^2)*$C$8+$C$7*SQRT($C$8)*BK78) -> 1.4347235
B20: Path 10 | C20: =$C$5 -> 11.5 | D20: =C20*EXP(($C$6-0.5*$C$7^2)*$C$8+$C$7*SQRT($C$8)*D79) -> 11.61389 | E20: =D20*EXP(($C$6-0.5*$C$7^2)*$C$8+$C$7*SQRT($C$8)*E79) -> 11.80568 | F20: =E20*EXP(($C$6-0.5*$C$7^2)*$C$8+$C$7*SQRT($C$8)*F79) -> 11.600669 | G20: =F20*EXP(($C$6-0.5*$C$7^2)*$C$8+$C$7*SQRT($C$8)*G79) -> 11.071046 | H20: =G20*EXP(($C$6-0.5*$C$7^2)*$C$8+$C$7*SQRT($C$8)*H79) -> 10.624545 | I20: =H20*EXP(($C$6-0.5*$C$7^2)*$C$8+$C$7*SQRT($C$8)*I79) -> 9.5435024 | J20: =I20*EXP(($C$6-0.5*$C$7^2)*$C$8+$C$7*SQRT($C$8)*J79) -> 9.2635932 | K20: =J20*EXP(($C$6-0.5*$C$7^2)*$C$8+$C$7*SQRT($C$8)*K79) -> 8.7171214 | ... BK20: =BJ20*EXP(($C$6-0.5*$C$7^2)*$C$8+$C$7*SQRT($C$8)*BK79) -> 8.2148382
B21: Path 11 | C21: =$C$5 -> 11.5 | D21: =C21*EXP(($C$6-0.5*$C$7^2)*$C$8+$C$7*SQRT($C$8)*D80) -> 9.6053542 | E21: =D21*EXP(($C$6-0.5*$C$7^2)*$C$8+$C$7*SQRT($C$8)*E80) -> 10.235223 | F21: =E21*EXP(($C$6-0.5*$C$7^2)*$C$8+$C$7*SQRT($C$8)*F80) -> 10.171635 | G21: =F21*EXP(($C$6-0.5*$C$7^2)*$C$8+$C$7*SQRT($C$8)*G80) -> 10.519715 | H21: =G21*EXP(($C$6-0.5*$C$7^2)*$C$8+$C$7*SQRT($C$8)*H80) -> 8.7306312 | I21: =H21*EXP(($C$6-0.5*$C$7^2)*$C$8+$C$7*SQRT($C$8)*I80) -> 8.3863266 | J21: =I21*EXP(($C$6-0.5*$C$7^2)*$C$8+$C$7*SQRT($C$8)*J80) -> 7.8508123 | K21: =J21*EXP(($C$6-0.5*$C$7^2)*$C$8+$C$7*SQRT($C$8)*K80) -> 7.1394274 | ... BK21: =BJ21*EXP(($C$6-0.5*$C$7^2)*$C$8+$C$7*SQRT($C$8)*BK80) -> 10.476134
B22: Path 12 | C22: =$C$5 -> 11.5 | D22: =C22*EXP(($C$6-0.5*$C$7^2)*$C$8+$C$7*SQRT($C$8)*D81) -> 12.713029 | E22: =D22*EXP(($C$6-0.5*$C$7^2)*$C$8+$C$7*SQRT($C$8)*E81) -> 11.858622 | F22: =E22*EXP(($C$6-0.5*$C$7^2)*$C$8+$C$7*SQRT($C$8)*F81) -> 11.298795 | G22: =F22*EXP(($C$6-0.5*$C$7^2)*$C$8+$C$7*SQRT($C$8)*G81) -> 12.901986 | H22: =G22*EXP(($C$6-0.5*$C$7^2)*$C$8+$C$7*SQRT($C$8)*H81) -> 16.490161 | I22: =H22*EXP(($C$6-0.5*$C$7^2)*$C$8+$C$7*SQRT($C$8)*I81) -> 20.529542 | J22: =I22*EXP(($C$6-0.5*$C$7^2)*$C$8+$C$7*SQRT($C$8)*J81) -> 20.668627 | K22: =J22*EXP(($C$6-0.5*$C$7^2)*$C$8+$C$7*SQRT($C$8)*K81) -> 21.166954 | ... BK22: =BJ22*EXP(($C$6-0.5*$C$7^2)*$C$8+$C$7*SQRT($C$8)*BK81) -> 26.546019
... B60: Path 50 | C60: =$C$5 -> 11.5 | D60: =C60*EXP(($C$6-0.5*$C$7^2)*$C$8+$C$7*SQRT($C$8)*D119) -> 13.358459 | E60: =D60*EXP(($C$6-0.5*$C$7^2)*$C$8+$C$7*SQRT($C$8)*E119) -> 13.815095 | F60: =E60*EXP(($C$6-0.5*$C$7^2)*$C$8+$C$7*SQRT($C$8)*F119) -> 13.465829 | G60: =F60*EXP(($C$6-0.5*$C$7^2)*$C$8+$C$7*SQRT($C$8)*G119) -> 15.334558 | H60: =G60*EXP(($C$6-0.5*$C$7^2)*$C$8+$C$7*SQRT($C$8)*H119) -> 14.693539 | I60: =H60*EXP(($C$6-0.5*$C$7^2)*$C$8+$C$7*SQRT($C$8)*I119) -> 14.246826 | J60: =I60*EXP(($C$6-0.5*$C$7^2)*$C$8+$C$7*SQRT($C$8)*J119) -> 13.541538 | K60: =J60*EXP(($C$6-0.5*$C$7^2)*$C$8+$C$7*SQRT($C$8)*K119) -> 10.917749 | ... BK60: =BJ60*EXP(($C$6-0.5*$C$7^2)*$C$8+$C$7*SQRT($C$8)*BK119) -> 3.0950131
B69: Standard normal shocks (Python, seed 7)
B70: Path 1 | D70: 0.0012301534 | E70: 0.29874554 | F70: -0.27413786 | G70: -0.89059184 | H70: -0.45467079 | I70: -0.99164655 | J70: 0.060143603 | K70: 1.3402152 | L70: -0.49220652 | M70: -0.6204749 | N70: 0.48984205 | O70: 0.35688701 | P70: 0.10541425 | Q70: -0.93046804 | R70: -0.029251822 | S70: 0.69530319 | T70: -1.3442145 | U70: -0.45761576 | V70: -1.9012227 | W70: -1.2895377 | X70: -1.841735 | Y70: -0.23509113 | Z70: -1.2674465 | AA70: 0.27126436 | AB70: 0.15675109 | AC70: -0.18693094 | AD70: -2.5167597 | AE70: -0.5386929 | AF70: -0.048500945 | AG70: 0.11330899 | AH70: -1.5301358 | AI70: -0.47775328 | AJ70: -0.97851908 | AK70: -0.80883724 | AL70: 1.0608986 | AM70: -0.80753468 | AN70: -0.032521705 | AO70: 0.88438987 | AP70: -0.58360043 | AQ70: -0.11170195 | AR70: 0.11046414 | AS70: 0.063781774 | AT70: -1.2250558 | AU70: 0.07614023 | AV70: 1.3588234 | AW70: -1.5471447 | AX70: 0.85938269 | AY70: 0.11935403 | AZ70: -0.64147039 | BA70: 2.0004165 | BB70: 0.76225971 | BC70: -1.1992889 | BD70: 0.074516229 | BE70: 0.57668958 | BF70: -0.18878213 | BG70: 0.68291027 | BH70: -0.06651732 | BI70: 0.66724756 | BJ70: 1.4385226 | BK70: -0.67566225
B71: Path 2 | D71: 0.20313861 | E71: -0.46330758 | F71: 0.12726841 | G71: -1.1871945 | H71: -0.5793016 | I71: -0.19619597 | J71: 0.89876387 | K71: 1.145222 | L71: -1.3235278 | M71: -0.79464237 | N71: 0.64690342 | O71: -1.9924198 | P71: -0.46316987 | Q71: -0.097286926 | R71: 1.257015 | S71: 0.6894039 | T71: -0.32721342 | U71: -0.36857589 | V71: -0.2501954 | W71: 1.5235294 | X71: -0.42802494 | Y71: -0.30368039 | Z71: 0.35258907 | AA71: -0.12077045 | AB71: -0.19728423 | AC71: -1.1140671 | AD71: -0.011521468 | AE71: -0.44358122 | AF71: 1.1661278 | AG71: 0.6530885 | AH71: -0.024143613 | AI71: 0.66838102 | AJ71: -0.33986955 | AK71: 1.0521264 | AL71: -0.0053995607 | AM71: 0.58338235 | AN71: -1.2908932 | AO71: 0.34668005 | AP71: -1.6882041 | AQ71: -2.0353289 | AR71: -0.30447688 | AS71: -0.89992761 | AT71: 0.1640528 | AU71: 2.2447566 | AV71: -0.83172318 | AW71: -0.62394359 | AX71: 0.20540395 | AY71: 0.49301329 | AZ71: -0.17640607 | BA71: -0.20593033 | BB71: 0.70246296 | BC71: 0.51990764 | BD71: -1.0336758 | BE71: -0.079181319 | BF71: 0.035286849 | BG71: -1.0544846 | BH71: 0.2598391 | BI71: -0.85795648 | BJ71: 0.97206671 | BK71: 0.19274591
B72: Path 3 | D72: 0.089306486 | E72: -0.59102835 | F72: -0.11860982 | G72: -1.9977463 | H72: -1.1314075 | I72: 0.3628398 | J72: -2.128567 | K72: 0.84660852 | L72: -1.7460965 | M72: 0.7567385 | N72: -0.84549703 | O72: 0.77899108 | P72: 0.13095121 | Q72: -1.5368349 | R72: 1.2491487 | S72: 1.4417072 | T72: -0.065804906 | U72: -0.27391627 | V72: -0.15986697 | W72: -0.97515232 | X72: 1.0985868 | Y72: -0.54289193 | Z72: -0.051190413 | AA72: -0.7932964 | AB72: -0.6260731 | AC72: -1.2777252 | AD72: 1.2570693 | AE72: -0.15408757 | AF72: 0.96592162 | AG72: 0.013324597 | AH72: -0.69440353 | AI72: -0.32668526 | AJ72: -0.56023105 | AK72: 0.0079590992 | AL72: -0.37526684 | AM72: -0.29992172 | AN72: -1.3785747 | AO72: -0.80684593 | AP72: 1.6540575 | AQ72: -0.67123322 | AR72: -1.0540938 | AS72: 0.33732633 | AT72: 1.4072722 | AU72: -1.4540243 | AV72: -0.20852185 | AW72: -0.63205255 | AX72: -1.7610195 | AY72: 0.73492671 | AZ72: -0.023443919 | BA72: 0.071441844 | BB72: -0.75231147 | BC72: 0.45478416 | BD72: -0.53929735 | BE72: -0.14290321 | BF72: -1.1082608 | BG72: -1.2161028 | BH72: 1.3355319 | BI72: -0.5071047 | BJ72: 0.29168036 | BK72: -0.033790435
B73: Path 4 | D73: -0.4411452 | E73: -0.50796097 | F73: 0.63008259 | G73: -0.3018676 | H73: -0.15144365 | I73: 0.022221557 | J73: 1.1765083 | K73: 0.68051097 | L73: 0.38260027 | M73: -0.56357139 | N73: -1.3819687 | O73: 0.94952993 | P73: 0.96644713 | Q73: -0.1407084 | R73: 0.54188384 | S73: 0.78144305 | T73: 0.83118445 | U73: 0.92138347 | V73: -0.45561765 | W73: 1.514973 | X73: -1.2465931 | Y73: 0.86172308 | Z73: 0.49393208 | AA73: 0.87361911 | AB73: 1.8790083 | AC73: 1.4844455 | AD73: -1.1451769 | AE73: -1.6886716 | AF73: 0.81688906 | AG73: -1.0150124 | AH73: -0.012405389 | AI73: 0.83972748 | AJ73: -1.6437974 | AK73: -2.1099805 | AL73: 0.25929902 | AM73: 0.04438589 | AN73: -0.24580307 | AO73: 0.038534764 | AP73: -0.86051561 | AQ73: -1.5134944 | AR73: -0.16665485 | AS73: -0.97170869 | AT73: -1.6434813 | AU73: 0.50568107 | AV73: -0.061398628 | AW73: 0.40652854 | AX73: -0.98929494 | AY73: -0.65805879 | AZ73: -0.99904303 | BA73: -0.88664187 | BB73: 0.19540792 | BC73: -0.78297462 | BD73: 0.35606629 | BE73: 0.33975593 | BF73: 2.025161 | BG73: -1.392789 | BH73: 0.88790238 | BI73: -0.089487962 | BJ73: -0.01402973 | BK73: -1.4498638
B74: Path 5 | D74: -0.46019381 | E74: 0.74319726 | F74: -0.082478372 | G74: 0.08105437 | H74: -0.29071668 | I74: 1.1545697 | J74: -0.021472567 | K74: -2.2004157 | L74: -0.69207255 | M74: -1.9687966 | N74: -3.2514384 | O74: -0.53011535 | P74: 1.3335599 | Q74: 0.047119906 | R74: -1.1725457 | S74: -0.94069987 | T74: 1.1306132 | U74: 0.15762662 | V74: 0.047999242 | W74: -0.053461789 | X74: 0.038400262 | Y74: 0.80540565 | Z74: 0.5525673 | AA74: 0.2157047 | AB74: -1.0428684 | AC74: 0.51110876 | AD74: -0.68424708 | AE74: 1.0938457 | AF74: -1.2710508 | AG74: -0.13762098 | AH74: -0.0073582863 | AI74: -1.3246456 | AJ74: 1.7219716 | AK74: 1.4604068 | AL74: -0.46358376 | AM74: 0.77172117 | AN74: 0.37867607 | AO74: -2.6135595 | AP74: 0.25039802 | AQ74: -0.06134408 | AR74: 0.083217353 | AS74: -1.0768749 | AT74: -0.26934705 | AU74: -0.17825876 | AV74: 1.1880942 | AW74: 0.33442706 | AX74: -0.0055550302 | AY74: 1.52897 | AZ74: -0.55524793 | BA74: -0.3894303 | BB74: -1.816755 | BC74: 1.5691058 | BD74: 0.96433237 | BE74: 0.91684804 | BF74: 0.66889845 | BG74: 0.11014859 | BH74: 0.21548894 | BI74: -0.25200659 | BJ74: -0.20360043 | BK74: 0.054303612
B75: Path 6 | D75: 1.5118295 | E75: 0.5556879 | F75: -0.058460126 | G75: -0.57939205 | H75: -0.63499849 | I75: 1.602705 | J75: 0.5066873 | K75: 0.067550558 | L75: -0.34618184 | M75: -1.1090534 | N75: -0.066861558 | O75: 0.87365803 | P75: -0.39253725 | Q75: -0.22724258 | R75: -0.22103435 | S75: 0.10959437 | T75: -1.5930109 | U75: -0.23539835 | V75: -0.85439552 | W75: 0.88458503 | X75: -0.77059868 | Y75: 0.57704675 | Z75: 1.5244375 | AA75: -0.31359626 | AB75: -0.60157625 | AC75: 0.19143226 | AD75: -0.0020290276 | AE75: -0.99361635 | AF75: 0.46091942 | AG75: 2.0155161 | AH75: -0.258112 | AI75: -0.2028762 | AJ75: -1.044932 | AK75: 0.31908845 | AL75: -1.2469762 | AM75: -1.106931 | AN75: 1.2796673 | AO75: -0.90545306 | AP75: 1.0813576 | AQ75: 1.524358 | AR75: 0.25932646 | AS75: 0.5533914 | AT75: 1.9522509 | AU75: -0.1967284 | AV75: -0.5930058 | AW75: -1.3532311 | AX75: 0.04170708 | AY75: 1.4791442 | AZ75: 0.95959538 | BA75: -0.94209124 | BB75: -0.85537538 | BC75: -0.50417123 | BD75: 0.29226808 | BE75: -0.20531143 | BF75: 0.21445395 | BG75: 0.29673938 | BH75: -0.29877359 | BI75: -0.040173942 | BJ75: 0.20659238 | BK75: -0.083969704
B76: Path 7 | D76: 0.50352087 | E76: 1.8708758 | F76: 0.59197228 | G76: 0.055810546 | H76: -1.6861186 | I76: 0.38795709 | J76: -1.9466784 | K76: -1.4090341 | L76: 0.85463925 | M76: 0.70623506 | N76: -0.149939 | O76: -1.7100111 | P76: -0.37134852 | Q76: -0.67873832 | R76: 0.63684075 | S76: 2.2577305 | T76: 0.21693049 | U76: -0.77931113 | V76: -1.1705515 | W76: -0.056094281 | X76: -0.17679319 | Y76: -1.1515192 | Z76: 0.11635524 | AA76: -1.1509135 | AB76: 1.1121073 | AC76: 1.0626506 | AD76: 1.0847513 | AE76: -0.47405047 | AF76: 0.51452056 | AG76: -0.13206951 | AH76: -0.38881206 | AI76: -0.33914566 | AJ76: -1.2997153 | AK76: -1.4438637 | AL76: 0.79431479 | AM76: -0.1912354 | AN76: 0.21642485 | AO76: 1.0017104 | AP76: -1.7331325 | AQ76: -0.78413007 | AR76: 0.17533484 | AS76: 0.39209479 | AT76: -0.37707445 | AU76: 1.0291792 | AV76: 0.21039494 | AW76: -1.2133821 | AX76: -0.93076378 | AY76: 0.80547106 | AZ76: 0.46383146 | BA76: -1.8990612 | BB76: 1.3477123 | BC76: 0.59802703 | BD76: 1.343343 | BE76: -0.38370088 | BF76: -0.29570622 | BG76: -1.1264571 | BH76: 2.5369296 | BI76: -0.17545423 | BJ76: 1.5875332 | BK76: -0.64729245
B77: Path 8 | D77: 0.16384119 | E77: -1.6713525 | F77: -0.38286715 | G77: 0.98375491 | H77: -1.2517438 | I77: 1.0722275 | J77: 0.33723782 | K77: -1.0439509 | L77: -0.50159727 | M77: -0.45906568 | N77: -0.049519338 | O77: -0.53614397 | P77: -0.8272879 | Q77: -0.3045877 | R77: -1.0268897 | S77: -1.2895266 | T77: -0.048176482 | U77: 0.88287423 | V77: -1.5293717 | W77: 0.0035081515 | X77: -0.64995619 | Y77: -0.97714544 | Z77: 0.85343765 | AA77: -0.51816969 | AB77: 1.4983017 | AC77: -0.77983936 | AD77: 0.38650199 | AE77: -0.22728301 | AF77: -0.75402181 | AG77: 0.58767504 | AH77: -0.15498257 | AI77: 0.60321058 | AJ77: -0.047291507 | AK77: -1.0858163 | AL77: -0.10206924 | AM77: 0.05195517 | AN77: 0.95846295 | AO77: -0.90626901 | AP77: -0.039329853 | AQ77: -1.7218787 | AR77: 0.65149306 | AS77: -1.081483 | AT77: -1.8063595 | AU77: -0.059216834 | AV77: 1.105685 | AW77: -1.5244469 | AX77: -1.0880356 | AY77: -0.74327489 | AZ77: -1.1294966 | BA77: 0.37942789 | BB77: -0.80736745 | BC77: -0.72151474 | BD77: 0.5833054 | BE77: -0.75551463 | BF77: 0.4327801 | BG77: -0.97138517 | BH77: -1.2121385 | BI77: -1.8354493 | BJ77: 1.8612028 | BK77: -0.32025903
B78: Path 9 | D78: 0.24393337 | E78: -0.031049509 | F78: 0.15996176 | G78: 0.049686479 | H78: 1.908217 | I78: -1.0389266 | J78: -1.5574621 | K78: -1.0119597 | L78: -1.334709 | M78: 0.74696205 | N78: 0.82037821 | O78: -0.96131555 | P78: -1.3904358 | Q78: -0.35479665 | R78: 1.3911239 | S78: -2.8195694 | T78: 0.52662677 | U78: -1.0757552 | V78: 1.0403671 | W78: -1.0779239 | X78: -0.28541583 | Y78: -1.5062791 | Z78: -0.97725785 | AA78: 1.3858392 | AB78: 0.82057869 | AC78: -0.40166815 | AD78: -0.87017237 | AE78: -1.8938071 | AF78: -0.39365671 | AG78: -0.030903253 | AH78: -0.084054358 | AI78: -0.093791928 | AJ78: -1.1218096 | AK78: -0.066273885 | AL78: -0.03867338 | AM78: 1.290562 | AN78: 1.8667335 | AO78: -0.13698903 | AP78: -0.76630595 | AQ78: -0.06498213 | AR78: -0.60762128 | AS78: -0.74243382 | AT78: -0.058650152 | AU78: -1.0433044 | AV78: 0.60610675 | AW78: -0.10391555 | AX78: 0.25000831 | AY78: -0.18294004 | AZ78: -0.72725445 | BA78: -0.94795956 | BB78: -0.237276 | BC78: -0.54876034 | BD78: 0.23390133 | BE78: -0.0044317032 | BF78: -1.3623067 | BG78: 0.067121299 | BH78: -1.3428604 | BI78: -0.61647763 | BJ78: -0.29435361 | BK78: -2.0752733
B79: Path 10 | D79: 0.091507448 | E79: 0.15098335 | F79: -0.15802419 | G79: -0.42431727 | H79: -0.37360366 | I79: -0.97653947 | J79: -0.26970037 | K79: -0.5526118 | L79: 0.091685393 | M79: -1.2041361 | N79: 0.23558991 | O79: 0.14321889 | P79: -0.14156283 | Q79: -0.43920482 | R79: 0.55233989 | S79: -1.6646017 | T79: 0.46045334 | U79: 0.24303747 | V79: 0.28337629 | W79: 0.38331259 | X79: -0.65364441 | Y79: -0.25946006 | Z79: 0.63705833 | AA79: 0.43063924 | AB79: 0.20671277 | AC79: -1.5143202 | AD79: 0.53788711 | AE79: 1.169471 | AF79: 1.0096715 | AG79: 0.23387805 | AH79: -1.5576786 | AI79: 0.94254481 | AJ79: -0.14725464 | AK79: -2.5325196 | AL79: 0.3772074 | AM79: -1.4921718 | AN79: -1.2964406 | AO79: -0.63495889 | AP79: 1.2725912 | AQ79: -0.37084535 | AR79: 0.27099159 | AS79: 1.747968 | AT79: 1.5940298 | AU79: -0.10335342 | AV79: -0.24152102 | AW79: -1.2608706 | AX79: -0.69445807 | AY79: 0.42535835 | AZ79: 0.39573076 | BA79: 0.11023823 | BB79: 0.99480166 | BC79: -0.77236801 | BD79: -0.05607652 | BE79: 0.73124299 | BF79: 0.58414591 | BG79: 1.0709458 | BH79: 0.39702041 | BI79: -0.30940256 | BJ79: 0.36219226 | BK79: -1.0025952
B80: Path 11 | D80: -1.6394593 | E80: 0.58067178 | F80: -0.055140333 | G80: 0.30840963 | H80: -1.6976844 | I80: -0.36511402 | J80: -0.59985711 | K80: -0.86421211 | L80: -2.255015 | M80: -0.33487348 | N80: 0.89730429 | O80: 0.38099772 | P80: -0.60094661 | Q80: -0.014875972 | R80: 0.75680008 | S80: -2.7604179 | T80: -0.12453655 | U80: 0.54320015 | V80: 0.68212863 | W80: 1.7007302 | X80: 1.1350457 | Y80: 0.31256283 | Z80: 0.30197601 | AA80: 0.78694535 | AB80: -0.53932699 | AC80: -0.040188055 | AD80: 0.906239 | AE80: 1.9574452 | AF80: -0.15926731 | AG80: -0.048400689 | AH80: 0.19848019 | AI80: 1.3432037 | AJ80: -0.030313304 | AK80: 1.469359 | AL80: -0.96665722 | AM80: -0.1860363 | AN80: -0.19816516 | AO80: 0.78650572 | AP80: 1.0452604 | AQ80: -1.5094444 | AR80: -0.91511763 | AS80: 0.33685248 | AT80: -0.65869365 | AU80: -1.5224278 | AV80: 1.03848 | AW80: 0.49397008 | AX80: 0.4931775 | AY80: -0.47544572 | AZ80: 1.0289385 | BA80: -0.23996 | BB80: 1.0964353 | BC80: -0.91166515 | BD80: -0.85413545 | BE80: 0.20466321 | BF80: -0.70233215 | BG80: 0.67545107 | BH80: 0.26008774 | BI80: -0.92297122 | BJ80: 0.072865601 | BK80: -0.35127769
B81: Path 12 | D81: 0.91583283 | E81: -0.63255298 | F81: -0.4391731 | G81: 1.2112369 | H81: 2.2385934 | I81: 1.9990087 | J81: 0.063223012 | K81: 0.21885471 | L81: 1.5334587 | M81: -0.12443481 | N81: -0.97634914 | O81: 0.1168756 | P81: 0.45151678 | Q81: -0.82914962 | R81: -1.6462311 | S81: -1.4367295 | T81: 0.66542928 | U81: -0.75837652 | V81: -0.14134709 | W81: 0.21255868 | X81: 0.61914088 | Y81: -0.3349028 | Z81: 0.4987157 | AA81: -0.89006029 | AB81: -0.36171403 | AC81: -1.0244156 | AD81: 1.1317672 | AE81: -0.027083228 | AF81: -0.73930749 | AG81: -0.3523718 | AH81: -0.22172848 | AI81: 0.70051979 | AJ81: -1.5956362 | AK81: -1.0372058 | AL81: -0.37810725 | AM81: 2.5323058 | AN81: 0.95567889 | AO81: -0.11145168 | AP81: 0.71199958 | AQ81: 2.0574362 | AR81: -0.23374393 | AS81: -0.36641334 | AT81: 1.2119435 | AU81: 0.4941755 | AV81: 0.67133316 | AW81: -0.5082224 | AX81: 1.9242031 | AY81: 1.7095908 | AZ81: 0.56594779 | BA81: 0.68428984 | BB81: -2.0272609 | BC81: 0.63770979 | BD81: -0.19410859 | BE81: 0.43390571 | BF81: 0.68245941 | BG81: -0.34129177 | BH81: -1.6904818 | BI81: 0.36787457 | BJ81: -0.74138365 | BK81: -0.33019409
... B119: Path 50 | D119: 1.3672819 | E119: 0.30808013 | F119: -0.23175918 | G119: 1.1863362 | H119: -0.38759412 | I119: -0.27977551 | J119: -0.46117154 | K119: -1.9616725 | L119: 0.86425699 | M119: -1.2090845 | N119: -0.56869272 | O119: -0.74387188 | P119: 0.7269906 | Q119: -0.068582783 | R119: 0.01541655 | S119: -1.6794598 | T119: -0.087437048 | U119: -1.4763331 | V119: 0.307197 | W119: 0.36672299 | X119: -0.017397483 | Y119: 2.0431437 | Z119: 0.52772891 | AA119: 0.59582417 | AB119: 0.14231135 | AC119: -0.19275808 | AD119: 0.96591826 | AE119: 1.1014495 | AF119: -1.3011604 | AG119: 1.0544896 | AH119: 0.5138232 | AI119: 0.96070007 | AJ119: 0.46617878 | AK119: -1.2442697 | AL119: -1.1729165 | AM119: 1.8245905 | AN119: 0.25242387 | AO119: -1.4172555 | AP119: 0.348132 | AQ119: -0.3621236 | AR119: -1.843414 | AS119: -2.2901882 | AT119: -1.6026667 | AU119: 0.27179254 | AV119: -0.048072218 | AW119: -0.24915919 | AX119: 0.28467815 | AY119: 0.60113043 | AZ119: -2.1025074 | BA119: -0.30115118 | BB119: -0.82791465 | BC119: -1.233195 | BD119: -0.54720128 | BE119: -0.1228721 | BF119: -0.26635646 | BG119: -1.4546673 | BH119: -0.48314951 | BI119: 2.0158329 | BJ119: -1.0545548 | BK119: -1.687093

Sheet Checks
B2: Checks
B3: Each live iteration recomputed by the Python engine (values) against the Excel formula; valid at the default inputs
B5: Check | C5: Excel | D5: Python | E5: Difference | F5: Iter | G5: Python value | H5: Gap vs Excel
B6: Base case value per share | C6: ='DCF Base Case'!C36 -> 14.916493 | D6: 14.916493 | E6: =C6-D6 -> 0 | F6: 1 | G6: 14.218986 | H6: =ABS(Simulation!U6-G6) -> 1.2558843e-12
B7: Median of the live iterations | C7: =Results!C7 -> 12.553903 | D7: 12.553903 | E7: =C7-D7 -> 0 | F7: 2 | G7: 16.848533 | H7: =ABS(Simulation!U7-G7) -> 8.8853369e-12
B8: Mean of the live iterations | C8: =Results!C6 -> 13.40285 | D8: 13.40285 | E8: =C8-D8 -> -4.156675e-13 | F8: 3 | G8: 9.7005296 | H8: =ABS(Simulation!U8-G8) -> 4.1584514e-12
B9: P5 of the live iterations | C9: =Results!C9 -> 5.4605247 | D9: 5.4605247 | E9: =C9-D9 -> -4.9737992e-14 | F9: 4 | G9: 11.867673 | H9: =ABS(Simulation!U9-G9) -> 5.7163163e-12
B10: P95 of the live iterations | C10: =Results!C13 -> 24.176302 | D10: 24.176302 | E10: =C10-D10 -> -6.7643668e-12 | F10: 5 | G10: 8.8115818 | H10: =ABS(Simulation!U10-G10) -> 1.9735324e-12
B11: Windfall: median if surcharge | C11: =Windfall!M7 -> 10.019161 | D11: 10.019161 | E11: =C11-D11 -> 1.5507595e-12 | F11: 6 | G11: 5.619319 | H11: =ABS(Simulation!U11-G11) -> 7.6072482e-12
B12: Windfall: median, no surcharge | C12: =Windfall!N7 -> 13.561292 | D12: 13.561292 | E12: =C12-D12 -> -6.0467187e-12 | F12: 7 | G12: 19.2696 | H12: =ABS(Simulation!U12-G12) -> 3.8014036e-12
F13: 8 | G13: 18.796719 | H13: =ABS(Simulation!U13-G13) -> 3.3359981e-12
B14: Largest gap, row by row (€) | C14: =MAX(H6:H2005) -> 2.5624303e-10 | F14: 9 | G14: 9.7992702 | H14: =ABS(Simulation!U14-G14) -> 2.6307845e-12
B15: Status | C15: =IF(AND(C14<0.000001,MAX(E6:E12)<0.000001,MIN(E6:E12)>-0.000001),"OK: Python = Excel","Check: inputs changed") -> OK: Python = Excel | F15: 10 | G15: 20.321405 | H15: =ABS(Simulation!U15-G15) -> 3.6450842e-12
F16: 11 | G16: 10.910596 | H16: =ABS(Simulation!U16-G16) -> 2.1209701e-12
F17: 12 | G17: 19.368747 | H17: =ABS(Simulation!U17-G17) -> 2.7746694e-12
F18: 13 | G18: 17.550726 | H18: =ABS(Simulation!U18-G18) -> 4.3840487e-12
F19: 14 | G19: 9.543534 | H19: =ABS(Simulation!U19-G19) -> 1.0338397e-11
F20: 15 | G20: 10.212265 | H20: =ABS(Simulation!U20-G20) -> 4.1016079e-12
F21: 16 | G21: 10.067439 | H21: =ABS(Simulation!U21-G21) -> 1.5649704e-12
F22: 17 | G22: 10.756215 | H22: =ABS(Simulation!U22-G22) -> 5.7909233e-13
F23: 18 | G23: 14.902679 | H23: =ABS(Simulation!U23-G23) -> 3.7161385e-12
F24: 19 | G24: 23.339374 | H24: =ABS(Simulation!U24-G24) -> 1.5667467e-12
F25: 20 | G25: 8.1212577 | H25: =ABS(Simulation!U25-G25) -> 1.2221335e-12
F26: 21 | G26: 7.0044615 | H26: =ABS(Simulation!U26-G26) -> 1.0249579e-12
F27: 22 | G27: 10.835445 | H27: =ABS(Simulation!U27-G27) -> 1.5614177e-12
... F2005: 2000 | G2005: 25.600126 | H2005: =ABS(Simulation!U2005-G2005) -> 2.2097879e-12
